Workbook

Sheet Pre-condiciones obligatorias
B2: No. | C2: Descripción | D2: Responsable | E2: Fecha de Finalización
B3: 0 | C3: Segregación de BO por país Crear perfiles para Segmento Multilatino
B4: 1 | C4: Criterios de Alta en Back Office
B5: 2 | C5: Carga de Matriz de Productos y permisos
B6: 3 | C6: Carga de Enumerador de Error
B7: 4 | C7: Disponibiliad de Core
B8: 5 | C8: Migración de Destinos Autorizados

Sheet Contenido
A1: P | B1: Estado | C1: Responsable | D1: Observaciones | E1: Todos | F1: Colombia | G1: Panama | H1: Costa Rica | I1: Honduras | J1: El Salvador | K1: Miami | L1: Total
A2: HU001_PER - Single sign on - SSO | B2: Entregado | C2: Devora | E2: ='HU001_PER - Single sign on - SS'!M2 -> 43 | F2: - | G2: - | H2: - | I2: - | J2: - | K2: - | L2: ='HU001_PER - Single sign on - SS'!M2 -> 43
A3: HU002_PER - Home Módulo Regional | B3: Entregado | C3: Sandra | E3: ='HU002_PER - Home Módulo Regiona'!L2 -> 45 | F3: ='HU001_PER - Single sign on - SS'!M3 -> 9 | G3: - | H3: - | I3: - | J3: - | K3: - | L3: ='HU002_PER - Home Módulo Regiona'!L2 -> 45
A4: HU003_PER - Accesos Rápidos | B4: Entregado | C4: Sandra | E4: ='HU003_PER - Accesos Rápidos'!K3 -> 36 | F4: - | G4: - | H4: - | I4: - | J4: - | K4: - | L4: ='HU003_PER - Accesos Rápidos'!K3 -> 36
A5: HU004_PER - Posición consolidada cuentas de ahorro y corriente | B5: Entregado | C5: Sandra | E5: ='HU004 - Posición Consolidada cu'!M9 -> 23 | F5: ='HU004 - Posición Consolidada cu'!M3 -> 2 | G5: ='HU004 - Posición Consolidada cu'!M4 -> 2 | H5: ='HU004 - Posición Consolidada cu'!M5 -> 2 | I5: ='HU004 - Posición Consolidada cu'!M6 -> 2 | J5: ='HU004 - Posición Consolidada cu'!M7 -> 2 | K5: ='HU004 - Posición Consolidada cu'!M8 -> 2 | L5: ='HU004 - Posición Consolidada cu'!M2 -> 35
A6: HU005_PER - Consulta detallada de cuentas | B6: Entregado | C6: Sandra | E6: ='HU005_PER - Consulta detallada '!M3 -> 45 | F6: ='HU006_PER - Detalle movimiento '!M3 -> 3 | G6: ='HU005_PER - Consulta detallada '!M5 -> 3 | H6: ='HU005_PER - Consulta detallada '!M6 -> 3 | I6: ='HU005_PER - Consulta detallada '!M7 -> 3 | J6: ='HU005_PER - Consulta detallada '!M8 -> 3 | K6: ='HU005_PER - Consulta detallada '!M9 -> 3 | L6: ='HU005_PER - Consulta detallada '!M2 -> 63
A7: HU006_PER - Detalle movimiento de cuenta | B7: Entregado | C7: Sandra | E7: ='HU006_PER - Detalle movimiento '!M9 -> 21 | F7: ='HU006_PER - Detalle movimiento '!M3 -> 3 | G7: ='HU006_PER - Detalle movimiento '!M4 -> 3 | H7: ='HU006_PER - Detalle movimiento '!M5 -> 3 | I7: ='HU006_PER - Detalle movimiento '!M6 -> 3 | J7: ='HU006_PER - Detalle movimiento '!M7 -> 3 | K7: ='HU006_PER - Detalle movimiento '!M8 -> 3 | L7: ='HU006_PER - Detalle movimiento '!M2 -> 39
A8: HU007_PER - Consulta y descarga de extractos (Estados de cuenta) | B8: Entregado | C8: Sandra | E8: ='HU007_PER - Consulta y descarga'!N3 -> 7 | F8: ='HU007_PER - Consulta y descarga'!N9 -> 2 | G8: ='HU007_PER - Consulta y descarga'!N7 -> 2 | H8: ='HU007_PER - Consulta y descarga'!N6 -> 2 | I8: ='HU007_PER - Consulta y descarga'!N5 -> 2 | J8: ='HU007_PER - Consulta y descarga'!N4 -> 2 | K8: ='HU007_PER - Consulta y descarga'!N8 -> 2 | L8: ='HU007_PER - Consulta y descarga'!N2 -> 19
A9: HU008_PER - Módulo de administración Banco | B9: Entregado | C9: Katie | D9: Modificar | E9: ='HU008_PER - Módulo de administr'!M2 -> 135 | F9: - | G9: - | H9: - | I9: - | J9: - | K9: - | L9: ='HU008_PER - Módulo de administr'!M2 -> 135
A10: HU009_PER - Administración cliente / Grupo de Productos | B10: Entregado | C10: Katie | E10: ='HU009_PER - Grupo de Productos'!M2 -> 211 | F10: - | G10: - | H10: - | I10: - | J10: - | K10: - | L10: ='HU009_PER - Grupo de Productos'!M2 -> 211
A11: HU010_PER - Administración cliente / Usuarios | B11: Entregado | C11: Katie | E11: ='HU010_PER - Administración clie'!N2 -> 424 | F11: - | G11: - | H11: - | I11: - | J11: - | K11: - | L11: ='HU010_PER - Administración clie'!N2 -> 424
A12: HU011_PER - Administración cliente / Esquema de Firmas | B12: Entregado | C12: Katie | E12: ='HU011_PER - Esquema de Firmas'!N2 -> 219 | F12: - | G12: - | H12: - | I12: - | J12: - | K12: - | L12: ='HU011_PER - Esquema de Firmas'!N2 -> 219
A13: HU012_PER - Destinos Autorizados CAM | B13: Entregado | C13: Devora | D13: Modificar | E13: ='HU012_PER - Destinos Autorizado'!M3 -> 44 | F13: ='HU012_PER - Destinos Autorizado'!M4 -> 0 | G13: ='HU012_PER - Destinos Autorizado'!M5 -> 14 | H13: ='HU012_PER - Destinos Autorizado'!M6 -> 15 | I13: ='HU012_PER - Destinos Autorizado'!M7 -> 12 | J13: ='HU012_PER - Destinos Autorizado'!M8 -> 6 | K13: ='HU012_PER - Destinos Autorizado'!M9 -> 0 | L13: ='HU012_PER - Destinos Autorizado'!M2 -> 91
A14: HU013_PER - Transferencias Regionales CAM / A Cuentas Propias | B14: Entregado | C14: Sandra | E14: ='HU013_PER - Transferencias Regi'!O6 -> 45 | F14: - | G14: ='HU013_PER - Transferencias Regi'!O2 -> 74 | H14: ='HU013_PER - Transferencias Regi'!O3 -> 76 | I14: ='HU013_PER - Transferencias Regi'!O4 -> 74 | J14: ='HU013_PER - Transferencias Regi'!O5 -> 71 | K14: - | L14: ='HU013_PER - Transferencias Regi'!O1 -> 340
A15: HU014_PER - Transferencias Regionales CAM / A Terceros | B15: Entregado | C15: Devora | D15: Modificar | E15: ='HU014_PER - Transferencias Regi'!L7 -> 20 | F15: - | G15: ='HU014_PER - Transferencias Regi'!L3 -> 63 | H15: ='HU014_PER - Transferencias Regi'!L4 -> 65 | I15: ='HU014_PER - Transferencias Regi'!L5 -> 52 | J15: ='HU014_PER - Transferencias Regi'!L6 -> 45 | K15: - | L15: ='HU014_PER - Transferencias Regi'!L2 -> 245
A16: HU015_PER - Transferencias Regionales CAM / Consultas | B16: Entregado | C16: Fatimita | E16: ='HU015_PER - Transferencias Regi'!M3 -> 25 | F16: - | G16: - | H16: - | I16: - | J16: ='HU015_PER - Transferencias Regi'!M4 -> 1 | K16: - | L16: ='HU015_PER - Transferencias Regi'!M2 -> 26
A17: HU016_PER - Transferencias regionales CAM / Programadas | B17: Entregado | C17: Fatimita | D17: Modificar | E17: ='HU016_PER - Transferencias regi'!M3 -> 50 | F17: - | G17: - | H17: - | I17: - | J17: - | K17: - | L17: ='HU016_PER - Transferencias regi'!M2 -> 50
A18: HU017_PER - Autorizaciones transversal | B18: Entregado | C18: Sandra | E18: ='HU017_PER - Autorizaciones tran'!M9 -> 63 | F18: ='HU017_PER - Autorizaciones tran'!M3 -> 16 | G18: ='HU017_PER - Autorizaciones tran'!M4 -> 2 | H18: ='HU017_PER - Autorizaciones tran'!M5 -> 2 | I18: ='HU017_PER - Autorizaciones tran'!M6 -> 2 | J18: ='HU017_PER - Autorizaciones tran'!M7 -> 1 | K18: ='HU017_PER - Autorizaciones tran'!M8 -> 2 | L18: ='HU017_PER - Autorizaciones tran'!M2 -> 88
A19: HU018_PER - Módulo Autorizaciones | B19: N/A | C19: Katie | E19: ='HU018_PER - Módulo Autorizacion'!M2 -> 101 | F19: - | G19: - | H19: - | I19: - | J19: - | K19: - | L19: ='HU018_PER - Módulo Autorizacion'!M2 -> 101
A20: HU019_PER - Buzón Notificaciones | B20: Entregado | C20: Sandra | E20: ='HU019_PER - Buzón Notificacione'!M3 -> 26 | F20: - | G20: - | H20: - | I20: - | J20: - | K20: - | L20: ='HU019_PER - Buzón Notificacione'!M2 -> 27
A21: HU020_PER - Banners | B21: Entregado | C21: Sandra | E21: ='HU020_PER - Banners'!M3 -> 47 | F21: - | G21: - | H21: - | I21: - | J21: - | K21: - | L21: ='HU020_PER - Banners'!M2 -> 47
A22: HU021_PER - Onboarding MVP PER | B22: N/A | C22: Diego | F22: - | G22: - | H22: - | I22: - | J22: - | K22: -
A23: HU022_PER - Migración Destinos Autorizados | B23: Entregado | C23: Devora | E23: ='HU022_PER - Migración Destinos '!M3 -> 4 | F23: - | G23: - | H23: - | I23: - | J23: - | K23: -
A24: Mensajeria Transversal PER | B24: N/A | E24: Enumerados | F24: - | G24: - | H24: - | I24: - | J24: - | K24: - | L24: ='HU022_PER - Migración Destinos '!M3 -> 4
A25: Camara Transferencias Regionales CAM | B25: N/A | E25: N/A
E26: =SUM(E2:E25) -> 1634 | F26: =SUM(F2:F25) -> 35 | G26: =SUM(G2:G25) -> 163 | H26: =SUM(H2:H25) -> 168 | I26: =SUM(I2:I25) -> 150 | J26: =SUM(J2:J25) -> 134 | K26: =SUM(K2:K25) -> 12 | L26: =SUM(L2:L25) -> 2288
A27: Total de casos a ejecutar por cada país | F27: =SUM(E2,E3,E4,E5,E6,E7,E8,E9,E10,E11,E12,F26) -> 1244 | G27: =SUM($E$26,G26) -> 1797 | H27: =SUM(E26,H26) -> 1802 | I27: =SUM($E$26,I26) -> 1784 | J27: =SUM($E$26,J26) -> 1768 | K27: =SUM(E2,E3,E4,E5,E6,E7,E8,E9,E10,E11,E12,K26) -> 1221
A31: Entregable 1
A32: HU023: Cámara de Compensación
A33: HU024: Destinos Autorizados - Colombia
A34: HU025: Destinos Autorizados - Miami
A35: HU035: Destinos Autorizados Internacionales
A36: HU029: Transferencias Regionales Miami - Cuentas Propias
A37: HU030: Transferencias Regionales Miami - Cuentas a Terceros
A38: HU026: Transferencias Regionales Colombia - A cuentas propias
A39: HU027: Transferencias regionales Colombia - A terceros
A40: HU032: Programar transferencias regionales Miami - Cuentas propias
A41: HU033: Programar Transferencias Regionales Miami - Cuentas a terceros
A42: HU038: Consulta transferencias internacionales
... A52: HU036: Consulta y administración - Destinos Autorizados Internacionales

Sheet HU001_PER - Single sign on - SS
A1: Nomenclatura | B1: Requerimiento | C1: Título | D1: Precondición | E1: Descripción | F1: Resultado | G1: Responsable
A2: CP01 | B2: SSO | C2: No se visualice en el menú de Mis Productos la opción de Módulo Regional | D2: El usuario no debe estar marcado en Control Center Banca el Línea como usuarios Multilatino | E2: 1.Ingresar el usuario de Banca en línea de HN,PA,CR,SV,CO,MI 2.Seleccionar Empresa a utilizar 3.Ingresar en la posición consolidada 4.Validar los iconos que se muestran en el header | F2: El usuario no puede visualizar en el menú mis productos la opción de Módulo Regional | G2: Todos-Español SV Idioma Ingles | L2: Cantidad | M2: =COUNTA(G2:G44) -> 43
A3: CP02 | B3: SSO | C3: Validación usuario por Autoafiliación | D3: El usuario debe ser afiliado por medio de Autoadhesión, no por medio de Control Center y Cyberbank | E3: 1.Ingresar el usuario de Banca en línea de HN,PA,CR,SV,CO,MI 2.Seleccionar Empresa a utilizar 3.Ingresar en la posición consolidada 4.Validar los iconos que se muestran en el header ingrese de forma correcta | F3: El usuario no puede visualizar en el menú mis productos la opción de Módulo Regional | G3: Todos-Español SV Idioma Ingles | L3: Colombia | M3: =COUNTIF(G2:G44,"Colombia") -> 9
A4: CP03 | B4: SSO | C4: Ingreso con usuario creado por Control Center | D4: El usuario nuevo debe darse de alta desde CC BEL bajo el procedimiento normal -regulación local. El usuario no debe haberse marcado como usuario Multilatina | E4: 1.Ingresar el usuario de Banca en línea de HN,PA,CR,SV,CO,MI 2.Realiza el proceso de asignación de credenciales 4.Activa el soft token en caso aplique, finalizar el proceso exitoso 3.Ingresar en la posición consolidada | F4: El usuario ingresa las credenciales correctamente e inicia la sesión, al ingresar menú mis productos la opción de Módulo Regional no estará debe ser visible. | G4: Todos-Español SV Idioma Ingles
A5: CP04 | B5: SSO | C5: Ingreso con usuario creado por Cyberbank | D5: El usuario nuevo debe darse de alta desde Cyberbank bajo el procedimiento normal -regulación local. El usuario no debe haberse marcado como usuario Multilatina desde Control Center | E5: 1.Ingresar el usuario de Banca en línea de HN,PA,CR,SV,CO,MI 2.Realiza el proceso de asignación de credenciales 4.Activa el soft token, finalizar el proceso exitoso 3.Ingresar en la posición consolidada | F5: El usuario ingresa las credenciales correctamente e inicia la sesión, al ingresar a la posición consolidada no muestra en la parte superior el icono regional | G5: Todos-Español SV Idioma Ingles
A6: CP05 | B6: SSO | C6: Ingresar con usuario Inactivo-Inhabilitado | D6: El usuario debe estar en un estado diferente a Activo en BEL de su casa Matriz. No debe de estar marcado como usuario Multilatino | E6: 1.Ingresar el usuario de Banca en línea de HN,PA,CR,SV,CO 2.Ingresa las credenciales 3.BEL HN,PA,CR,SV,CO muestra un mensaje correspondiente a la administración de usuario 4. Si permite ingresar validará la posición consolidada 5.No permite ingresar no permitirá visualizar la selección de empresas ni posición consolidada | F6: El usuario no puede visualizar en el menú mis productos la opción de Módulo Regional | G6: Todos-Español SV Idioma Ingles
A7: CP06 | B7: SSO | C7: No debe poseer ningun método de autenticación Usuario Regional | D7: El usuario debe existir en BEL HN,PA,CR,SV El usuario debe tener estado activo Debe estar marcado como usuario multilatino No debe tener activado soft token-Detect ID | E7: 1.Ingresar el usuario de Banca en línea de HN,PA,CR,SV 2.Ingresa las credenciales 3.BEL HN,PA,CR,SV muestra un mensaje correspondiente a la administración de usuario> Según el enumerado de errores correspondiente al Core 4.Visualiza el módulo regional 5.Al realizar el switch al módulo muestra mensaje de Error | F7: El usuario no puede continuar con el proceso ya que es requerido que posea un método de autenticación y se active, en el front debe mostrar un mensaje de Error que le impida ver la posición consolidada. El caso se finaliza cuando muestra el mensaje de Error | G7: Todos-Español SV Idioma Ingles
A8: CP07 | B8: SSO | C8: Usuario Regional No debe permitir ingresar a Módulo Regional | D8: El usuario debe existir en BEL HN,PA,CR,SV Se debe encontrar activo el usuario Debe estar marcado como usuario multilatino Debe tener bloqueado o inactivo el método de autenticación | E8: 1.Ingresar el usuario de Banca en línea de HN,PA,CR,SV 2.Ingresa las credenciales 3.BEL HN,PA,CR,SV muestra un mensaje correspondiente a la administración de usuario 4.Visualiza el módulo regional 5.Ingresa al menú mis productos e ingresa a la opción de Módulo y muestra mensaje “abandonará la banca en línea para acceder al módulo regional” 6.Seleccionar Aceptar | F8: El usuario no puede continuar con el proceso ya que es requerido que posea el soft token y se active, en el front debe mostrar un mensaje de Error que le impida ver la posición consolidada. El caso se finaliza cuando muestra el mensaje de Error | G8: Todos-Español SV Idioma Ingles
A9: CP08 | B9: SSO | C9: Soft Token activo Usuario Regional Finaliza el proceso correctamente y ejecuta el switch al módulo | D9: El usuario debe existir en BEL HN,PA,CR,SV Se debe encontrar activo el usuario Debe estar marcado como cliente y usuario multilatino | E9: 1.Ingresar el usuario de Banca en línea de HN,PA,CR,SV 2.Ingresa las credenciales 3.BEL HN,PA,CR,SV muestra un mensaje correspondiente a la administración de usuario 4.Visualiza el módulo regional 5.Ingresa al menú mis productos y selecciona la opción de Módulo y muestra mensaje “abandonará la banca en línea para acceder al módulo regional” 6.Seleccionar Aceptar | F9: Si el usuario da clic en “aceptar” se debe trasladar los datos de la sesión para el módulo regional y la sesión de BEL quedará activa | G9: Todos-Español SV Idioma Ingles
A10: CP09 | B10: SSO | C10: Token activo Usuario Regional Cancela el switch al módulo | D10: El usuario debe existir en BEL HN,PA,CR,SV Se debe encontrar activo el usuario Debe estar marcado como usuario multilatino | E10: 1.Ingresar el usuario de Banca en línea de HN,PA,CR,SV 2.Ingresa las credenciales 3.BEL HN,PA,CR,SV muestra un mensaje correspondiente a la administración de usuario 4.Visualiza el módulo regional 5.Ingresa al menú mis productos y selecciona la opción de Módulo y muestra mensaje “abandonará la banca en línea para acceder al módulo regional” 6.Seleccionar Aceptar | F10: Si el usuario da clic en “cancelar” cierra el modal y permanece en la banca en línea. Continua la sesión activa en el canal. | G10: Todos-Español SV Idioma Ingles
A11: CP10 | B11: SSO | C11: Cliente Regional Falla en el proceso Por las condiciones de : Usuario Inactivo | D11: El usuario debe existir en BEL HN,PA,CR,SV Se debe encontrar inactivo el usuario Debe estar marcado como usuario multilatino Debe tener una token activo | E11: 1.Ingresar el usuario de Banca en línea de HN,PA,CR,SV 2.Ingresa las credenciales 3.BEL HN,PA,CR,SV muestra un mensaje correspondiente a la administración de usuario | F11: En caso que el canal no pueda confirmar la información ingresada por el usuario se debe presentar mensaje: “Intente más tarde, Por el momento, no es posible atender su solicitud.” | G11: Todos-Español SV Idioma Ingles
A12: CP11 | B12: SSO | C12: Cliente Regional Usuario con Sesión Activa en otro canal (APP locales o Super APP) | D12: El usuario debe existir en BEL HN,PA,CR,SV Se debe encontrar activo el usuario Debe estar marcado como cliente multilatino | E12: 1.Ingresa al App 2. No cierre la sesión 3.Ingresa a Banca en línea pero muestra un mensaje de error | F12: No permite ingresar a BEL debido a que existe una sesión activa Este mensaje dependerá de cada uno de los core si es enviado por correo electrónico o en el front muestra un mensaje de error al usuario. | G12: Todos-Español SV Idioma Ingles
A13: CP12 | B13: SSO | C13: Usuario de Portal realiza el ingreso y permite visualizar el tiempo de sesión Inactiva | D13: El usuario debe existir en BEL HN,PA,CR,SV Se debe encontrar activo el usuario Debe estar marcado como cliente multilatino Token activo | E13: 1.Ingresar el usuario de Banca en línea de HN,PA,CR,SV 2.Ingresa las credenciales 3.BEL HN,PA,CR,SV muestra un mensaje correspondiente a la administración de usuario 4.Visualiza en el menú 'Mis Productos' la opción de módulo regional 5.Ingresa al Módulo y muestra mensaje “abandonará la banca en línea para acceder al módulo regional” 6.Seleccionar Aceptar 7.Ingresa a Selección de Empresas 8.Validar en el header del canal que muestre los siguientes elementos: Nombre del usuario autenticado Rol Cambio de Idioma Ir a Banca Local Cerrar sesión | F13: En caso que no exista ninguna interacción y el límite del contador llegué a cero se presentará el mensaje: “Cerramos la sesión, Por seguridad cerramos esta sesión. Si quiere seguir usando el portal regional, ingrese nuevamente.” ¿Quiere seguir en el portal regional? “La sesión está inactiva y se cerrará en X Segundos, para seguir en el portal diríjase al botón “Continuar” No seleccionar ninguna opción Debe cerrar la sesión debido a inactividad Botón aceptar: Al dar clic en el botón de aceptar se debe informar que la sesión fue expirada. En los escenarios antes mencionados deberán liberar la sesión del usuario para evitar dejar atrapados la sesión. Los usuarios deben recibir notificaciones o confirmaciones por correo electrónico una vez que se haya realizado con éxito un login desde el canal tal cual cómo lo realizan desde la banca en línea o portal empresarial. | G13: Todos-Español SV Idioma Ingles
A14: CP13 | B14: SSO | C14: Usuario de Portal realiza el switch a la Banca Local según el país seleccionado Regresa a la BEL | D14: El usuario debe existir en BEL HN,PA,CR,SV Se debe encontrar activo el usuario Debe estar marcado como usuario multilatino Token activo | E14: 1.Ingresar el usuario de Banca en línea de HN,PA,CR,SV 2.Ingresa las credenciales 3.BEL HN,PA,CR,SV muestra un mensaje correspondiente a la administración de usuario 4.Visualiza el módulo regional 5.Ingresa al Módulo y muestra mensaje “abandonará la banca en línea para acceder al módulo regional” 6.Seleccionar Aceptar 7.Selecciona el botón de regresar a BEL del país indicado | F14: Si el usuario da clic en el botón Regresar a la banca en línea le permitirá cerrar la sesión de Portal y realizar el traslado a la Banca en línea seleccionada. El usuario puede ingresar a BEL-APP y no debe tener la sesión atrapada | G14: Todos-Español SV Idioma Ingles
A15: CP14 | B15: SSO | C15: Usuario de Portal realiza el ingreso y permite visualizar el tiempo de sesión Inactiva cierra la sesión exitosamente por Inactividad | D15: El usuario debe existir en BEL HN,PA,CR,SV Se debe encontrar activo el usuario Debe estar marcado como usuario multilatino | E15: El usuario debe existir en BEL HN,PA,CR,SV Se debe encontrar activo el usuario Debe estar marcado como usuario multilatino | F15: Ingresa a la opción de posición consolidada y muestra deja la sesión inactiva 30 segundos antes muestra un mensaje ¿Quiere seguir en el portal regional? “La sesión está inactiva y se cerrará en X Segundos, para seguir en el portal diríjase al botón “Cerrar sesión” Selecciona cerrar sesión. Al dar clic se cierra el módulo regional y confirma que la sesión fue finalizada exitosamente. No debe existir la sesión activa en BEL | G15: Todos-Español SV Idioma Ingles
... A44: CP43 | B44: SSO | C44: Usuario ingresa a BEL desde el Celular-Iphone - Safari Usuario de Portal realiza el ingreso y permite visualizar el tiempo de sesión Inactiva | D44: El usuario debe existir en BEL CO-MI Se debe encontrar activo el usuario Debe estar marcado como usuario multilatino | E44: 1.Ingresar el usuario de Banca en línea 2.Ingresa las credenciales 3.Muestra un mensaje correspondiente a la administración de usuario 4.Visualiza el módulo regional 5.Ingresa al Módulo y muestra mensaje “abandonará la banca en línea para acceder al módulo regional” 6.Seleccionar Aceptar 7.Ingresa a Posición consolidada | F44: Algunas BEL no tienen responsive por lo que puede variar dependiendo de cada país. Ingresa a la opción de posición consolidada y muestra deja la sesión inactiva 30 segundos antes muestra un mensaje ¿Quiere seguir en el portal regional? “La sesión está inactiva y se cerrará en X Segundos, para seguir en el portal diríjase al botón “Continuar” Selecciona Continuar y realiza logout Los usuarios deben recibir notificaciones o confirmaciones por correo electrónico una vez que se haya realizado con éxito un login desde el canal tal cual cómo lo realizan desde la banca en línea o portal empresarial. | G44: Todos-Español SV Idioma Ingles
C45: Agregar caso de prueba ingresando con holding

Sheet HU002_PER - Home Módulo Regiona
A1: Nomenclatura | B1: Requerimiento | C1: Título | D1: Precondición | E1: Descripción | F1: Resultado | G1: Pais Responsable
A2: CP01 | B2: Home Módulo Regional | C2: Criterio 1 - Home Módulo Regional: Funcionalidades asignadas de cada usuario | D2: Acceder al modulo con usuario autorizante y seleccionar todas las sociedades, el usuario debe estar en estado “activo” y habilitado en el PER | E2: Que el usuario pueda validar las funcionalidades asignadas de acuerdo al rol que posea (Consultor, preparador, aprobador, Administrador.) | F2: El usuario debe de poder visualizar el menu y operar en el modulo Home dependiendo el rol y funcionalidades asignadas | G2: Todos | K2: Consolidado | L2: =COUNTA(G2:G46) -> 45
A3: CP02 | B3: Home Módulo Regional | C3: Criterio 3 - Compatibilidad del ingreso al Modulo Regional | D3: Usuario operador debe de ingresar al modulo regional desde un dispositivo movil con sistema operativo Android | E3: Que el usuario ingrese desde su dispositivo movil Android y navegador google chrome, Se debe de tener consideracion que desde la versión responsive no se debe presentar la sección de accesos rápidos teniendo en cuenta que las funcionalidades transaccionales y administrativas no serán compatibles con dispositivos móviles. | F3: El ingreso a Home Módulo Regional debe de ser exitoso | G3: Todos
A4: CP03 | B4: Home Módulo Regional | C4: Criterio 3 - Compatibilidad del ingreso al Modulo Regional | D4: Usuario autorizante debe de ingresar al modulo regional desde un dispositivo movil con sistema operativo iOS | E4: Que el usuario ingrese desde su dispositivo movil IOS y navegador google chrome, Se debe de tener consideracion que desde la versión responsive no se debe presentar la sección de accesos rápidos teniendo en cuenta que las funcionalidades transaccionales y administrativas no serán compatibles con dispositivos móviles. | F4: El ingreso a Home Módulo Regional debe de ser exitoso | G4: Todos
A5: CP04 | B5: Home Módulo Regional | C5: Criterio 3 - Compatibilidad del ingreso al Modulo Regional | D5: El usuario debe de ingresar al modulo regional desde un dispositivo movil con sistema operativo iOS | E5: Que el usuario ingrese desde su dispositivo movil IOS y navegador zafari, Se debe de tener consideracion que desde la versión responsive no se debe presentar la sección de accesos rápidos teniendo en cuenta que las funcionalidades transaccionales y administrativas no serán compatibles con dispositivos móviles. | F5: El ingreso a Home Módulo Regional debe de ser exitoso | G5: Todos
A6: CP05 | B6: Home Módulo Regional | C6: Criterio 3 - Compatibilidad del ingreso al Modulo Regional | D6: El usuario debe de ingresar al modulo regional desde una tablet con sistema operativo Android | E6: Que el usuario ingrese desde una tablet Android y navegador google chrome | F6: El ingreso a Home Módulo Regional debe de ser exitoso | G6: Todos
A7: CP06 | B7: Home Módulo Regional | C7: Criterio 3 - Compatibilidad del ingreso al Modulo Regional | D7: El usuario debe de ingresar al modulo regional desde una tablet con sistema operativo Android | E7: Que el usuario ingrese desde una tablet IOS y navegador google chrome. | F7: El ingreso a Home Módulo Regional debe de ser exitoso | G7: Todos
A8: CP07 | B8: Home Módulo Regional | C8: Criterio 3 - Compatibilidad del ingreso al Modulo Regional | D8: El usuario debe de ingresar al modulo regional desde una tablet con sistema operativo Android | E8: Que el usuario ingrese desde una tablet IOS y navegador zafari. | F8: El ingreso a Home Módulo Regional debe de ser exitoso | G8: Todos
A9: CP08 | B9: Home Módulo Regional | C9: Criterio 3 - Compatibilidad del ingreso al Modulo Regional | D9: El usuario debe de ingresar al modulo regional desde una computadora de escritorio | E9: Que el usuario ingrese desde una computadora de escritorio el navegador google chrome. | F9: El ingreso a Home Módulo Regional debe de ser exitoso | G9: Todos
A10: CP09 | B10: Home Módulo Regional | C10: Criterio 3 - Compatibilidad del ingreso al Modulo Regional | D10: El usuario debe de ingresar al modulo regional desde una computadora de escritorio | E10: Que el usuario ingrese desde una computadora de escritorio utilizando el navegador Mozilla firefox | F10: El ingreso a Home Módulo Regional debe de ser exitoso | G10: Todos
A11: CP10 | B11: Home Módulo Regional | C11: Criterio 3 - Compatibilidad del ingreso al Modulo Regional | D11: El usuario debe de ingresar al modulo regional desde una computadora de escritorio | E11: Que el usuario ingrese desde una computadora de escritorio utilizando el navegador Edge | F11: El ingreso a Home Módulo Regional debe de ser exitoso | G11: Todos
A12: CP11 | B12: Home Módulo Regional | C12: Criterio 3 - Compatibilidad del ingreso al Modulo Regional | D12: El usuario debe de ingresar al modulo regional desde una computadora de escritorio | E12: Que el usuario ingrese desde una computadora de escritorio utilizando el navegador Explorer | F12: El ingreso a Home Módulo Regional debe de ser exitoso | G12: Todos
A13: CP12 | B13: Home Módulo Regional | C13: Criterio 3 - Compatibilidad del ingreso al Modulo Regional | D13: El usuario debe de ingresar al modulo regional desde una laptop | E13: Que el usuario ingrese desde su laptop utilizando el navegador google chrome. | F13: El ingreso a Home Módulo Regional debe de ser exitoso | G13: Todos
A14: CP13 | B14: Home Módulo Regional | C14: Criterio 3 - Compatibilidad del ingreso al Modulo Regional | D14: El usuario debe de ingresar al modulo regional desde una laptop | E14: Que el usuario ingrese desde su laptop utilizando el navegador Mozilla firefox | F14: El ingreso a Home Módulo Regional debe de ser exitoso | G14: Todos
... A20: CP19 | B20: Home Módulo Regional | C20: "Header" Cambio de idioma | D20: En la barra fija superior derecha se debe de mostrar el icono de cambio de idioma | E20: Validar que al selecconar el icono de cambio de idioma de español a inglés o viceversa sea de manera sencilla. | F20: El cambio de idioma se realice de forma exitosa de acuerdo al seleccionado por el usuario | G20: Todos
A21: CP20 | B21: Home Módulo Regional | C21: "Header" Última conexión / IP | D21: En la parte izquierda inferior se debe de mostrar la ultima conexion | E21: Validar que en la parte inferior se muestre el Último Ingreso y la IP: Ejemplo 11/02/2025 a las 04:08 PM, IP:168.243.173.52 | G21: Todos
A22: CP21 | B22: Home Módulo Regional | C22: "Header" Cerrar sesión | D22: En la barra fija superior se debe de mostrar un icono para cerra sesion | E22: Para el icono de cerrar sesion se deben validar los sigunetes paso: - Sea visible - A l dar click sobre el iconono muestre la pregunta ¿Quiere cerrar la sesión? y mostrará dos opciones “Volver” y "Cerrar sesión”- - Al das clic en “cerrar sesión” finaliza la sesión cerrando las ventanas abiertas - Al click en “Volver” solo cierra la ventana emergente y vuelve a mostrar la pantalla del home. | F22: El icono de cerrar sesion debe de funcinar de forma correcta de acuerdo a la opcion seleccionada | G22: Todos
A23: CP22 | B23: Home Módulo Regional | C23: "Header" Ingresar a la banca local | D23: En la barra fija superior se debe de mostrar un icono que direccione a la banca local | E23: Validar que dar clic en el icono "Banca local" muestre una pantalla con las 5 Opciones ( Colombia, Panamá, Costa Rica, Honduras y El Salvador) - Al seleccionar una de las opciones se cierra la sesion del canal de modulo regional y redirigirá al inicio de sesión del país de la banca local seleccionada | F23: Al seleccionar el pais de ingreso para la banca local, La sesion del modulo regional sea cerrada con exito y el usuario debe volver a autenticarse con los datos de "usuario y clave" personal para acceder al canal. | G23: Todos
A24: CP23 | B24: Home Módulo Regional | C24: Dashboard Home | D24: En el centro de la pantalla se debe de mostrar la información relevante para el usuario | E24: Validar las siguientes funcionalidades: - Empresas Conectadas: Se debe de mostrar un saludo con el nombre del grupo regional ej: “Hola,” Grupo Delpin, de acuerdo a como fue creado en CC - En la parte inferior se debe visualizar el nombre de la empresas que fue seleccionada al inicio de la sesión, y al lado del nombre se debe mostrar la bandera del país al cual pertenece. - Debe tener un elemento como un lápiz para que usuario puede editar la selección de empresas | F24: Que el nombre del grupo de empresa se muestre de forma correcta y el nombre de las empresas seleccionadas se muestre la bandera que corresponde a cada pais | G24: Todos
A25: CP24 | B25: Home Módulo Regional | C25: Dashboard Home "Editar" | D25: En la parte izquierda posterior se debe de mostrar como un lapiz en el que debe aparecer un tooltip con el texto “Editar”. | E25: En la opcion editar al efectuar una modificacion debe de mostrar el mensaje ¿Quiere abandonar esta edición? Si abandona, no se guardarán los cambios realizados. - Debe de permitir realizar búsqueda por país y nombre de acuerdo a las empresas seleccionadas al momento de ingresar al MR - Validar que se encuentren marcadas las casillas de “Checkbox” | F25: Que permita editar en la seleccion de empresas de manera exitosa | G25: Todos
A26: CP25 | B26: Home Módulo Regional | C26: Dashboard Home "Editar" | D26: En la parte izquierda posterior se debe de mostrar como un lapiz en el que debe aparecer un tooltip con el texto “Editar”. | E26: - Validar que al selecionar una nueva empresa se debe de habilitar el botón de “Aceptar”. - Validar que al dar clic en el boton de "Aceptar" si fue actualizada debe de mostrar “marcación exitosa”. si no se realiza mostrará: “Intente más tarde. No pudimos actualizar los cambios”. | F26: Que el boton de aceptar sea habilitado y funcione con exito | G26: Todos
A27: CP26 | B27: Home Módulo Regional | C27: Dashboard Home "Productos" | D27: De acuerdo a la selección de empresas realizadas en el inicio de sesion, el canal debe mostrar una tarjeta en donde se muestre por tipo de productos y “Saldo total consolidado”, para el MVP | E27: Validar que en la tarjeta (en color rojo) se muestre suma del saldo total consolidado de cada producto de acuerdo a lo habilitado de cada empresa - Cuenta ahorros, Corriente y ahorros maestra - El saldo se debe de visulaizar en dólares americanos de acuerdo a los productos asignados y de las empresas con las que el usuario inició sesión. | F27: Quen en la tarjeta roja se mustre el saldo consolidado de de acuerdo a las empresas seleccionadas | G27: Todos
A28: CP27 | B28: Home Módulo Regional | C28: Dashboard Home "Productos" | D28: El canal debe de mostrar los productos cuando el usuario ingrese al módulo regional realizando un llamado único por familias | E28: Cuando el usaurio este en Home se debe de validar que en la tarjeta se muestre el producto con la familia configurada en Control Center con prioridad 1. - Que al dar clic en el detalle se muestre los productos de las demas familias de acuerdo a lo seleccionado | F28: Los productos deben de mostrarse de forma exitosa de acuerdo a alas empresas seleccionadas al hacer login | G28: Todos
A29: CP28 | B29: Home Módulo Regional | C29: Dashboard Home "Tasas de Cambio" | D29: El canal debe mostrar el valor del dólar o tasa de referencia y incluir 2 campos para que el usuario pueda hacer la conversión de moneda local frente al dólar | E29: Validar que en al consultar la tasa de cambio se visualice los siguientes puntos: - Se beben de mostrar 2 campos para hacer la conversión de moneda - La conversion se tomara la del día de la operación - Debe de permitir ingresar valor y el canal debe actualizar de acuerdo a la conversión la equivalencia en la otra moneda.: | F29: Al consultar la tasa de cambio se debe de realizar la conversion de forma exitosa | G29: Todos
A30: CP29 | B30: Home Módulo Regional | C30: Dashboard Home "Accesos Rápidos" | D30: Los usuarios deben tener una opción que permita de acuerdo al rol y permisos sobre las funcionalidades del usuario | E30: Validar que en los acceso directos de acuerdo al rol del usuario permita las siguientes funcionalidades: - Asignar, editar o eliminar accesos a transacciones frecuentes - Al dar clic en unos de los atajos asignados previamente el canal lo debe redirigir a la opción seleccionada | F30: Al ingresar a los accesos rapidos permita editar o eliminar de forma exitosa, a ala vez al acceder a los atajos asignados el canal lo rediriga a la opcion seleccionada sin inconvenientes | G30: Todos
A31: CP30 | B31: Home Módulo Regional | C31: Dashboard Home "Banner expectativa" | D31: El area operativa del Banco pueda subir una imagen alusiva a la funcionalidad o producto del banco que se quiera promocionar | E31: En el canal se podran agregar hasta 5 banner - Se debe validar que se muestre en carrusel - Se debe contar con una flecha que permita cambiar al siguiente banner - Validar que el banner se muestre en un punto visible y que no afecte la vista de los productos del cliente | F31: Si se cuenta con mas de un banner se debe de mostrar una fecha que permita cambiar al siguiente, de forma exitosa | G31: Todos
A32: CP31 | B32: Home Módulo Regional | C32: Sidebar "Menú vertical izquierdo" | D32: Al lado izquierdo se debe de mostrar un menu fijo y en la barra fija superior el lodo de Davivienda | E32: Validar que en el menu izquierdo se muestren los siguientes iconos: - Inicio - Productos - Transferir - Autorizar - Administrar | F32: Que el menu se muestre en vertical al lado izquierdo, con los 5 iconos de forma correcta, | G32: Todos
A33: CP32 | B33: Home Módulo Regional | C33: Sidebar "Menú vertical izquierdo" | D33: El menu se debe de mostrar en forma vertical al lado izquierdo | E33: Validar la funcion de cada icono - Inicio: Al dar clic en este botón debe volver a cargar la pantalla del home o inicio. - Productos: Al dar clic en el botón debe mostrar la información asociada a la historia de usuario de Posición consolidada. Esta funcionalidad está habilitada a los usuarios que tengan la funcionalidad de consultas asignado. - Transferir: Este módulo solo estará habilitado para usuarios que tengan asignada la funcionalidad de “Transferencias Regionales en el MVP” - Autorizar: Esta opción solo estará habilitada para usuarios que tengan el rol de “autorizador” y “Administrador” y a su vez estén en un esquema de firmas. - Administrar: Este módulo solo debe ser visible para los usuarios que tengan perfil de Administrador, al dar clic en esta opción se habilita la opción de “Administrador de módulo regional” en la cual se pueden crear usuarios y grupos de productos. | F33: Cada icono debe de funcionar de forma correcta de acuerdo a la descripcion indicada | G33: Todos
... A46: CP45 | B46: Home Módulo Regional | C46: Logs | D46: Toda interacción que se realice en el módulo de Transferencias debe quedar almacenada para posterior consulta de los usuarios del control Center con el servicio asignado, quienes podrán consultar y visualizar Logs y descarga de informes del Registro completo de cualquier novedad realizada desde el módulo regional, El sistema debe generar y registrar de forma completa y precisa toda la información relacionados con la creación o cualquier novedad realizada, incluyendo toda la información detallada de los datos de entrada y salida, y cualquier error o excepción que se produzca durante el proceso. | E46: Validar que el usuario BO pueda realizar un filtro de busqueda : Fecha de novedad desde - hasta, País, Tipo de novedad | F46: La busqueda de logs debe ser exitosa | G46: Todos

Sheet HU007_PER - Consulta y descarga
A1: Nomenclatura | B1: Requerimiento | C1: Título | D1: Precondición | E1: Descripción | F1: Alcance | G1: Condición | H1: Resultado | I1: Pais Responsable
A2: CP01 | B2: Consulta y descarga de extractos (Estados de cuenta) | C2: Características - Consulta y descarga de extractos (Estados de cuenta) | D2: Ingresar al modulo regional con usuario administrador y seleccionar todas las sociedades, desde la posicion consolidada | E2: Al acceder a esta funcionlidad mientras carga la información que se mostrará en pantalla, se debe mostrar el “Skeleton” py posteriormente se debe de mostar la funcionalidad de "Estados de cuenta " | F2: Validar que se muestren la funionalidad de estados cuenta y que permita al usuario realizar la consulta y opcion de descargarlos | G2: Los productos a los que el usuario puede acceder para autogestionar la consulta y descarga de estados de cuentas (extractos) corresponde únicamente de productos asignados al usuario | H2: La descarga se debe de realizar con exito | I2: Todos | M2: Cantidad de Casos | N2: =SUM(N3:N9) -> 19
A3: CP02 | B3: Consulta y descarga de extractos (Estados de cuenta) | C3: Estados de Cuenta- Consulta y descarga de extractos | D3: Ingresar al modulo regional con usuario Autorizante - y seleccionar todas las sociedades | E3: Seleccionar el boton para realizar la descarga de “Estados de cuenta” al dar clic se actualice la pantalla donde se despliegue las siguientes opciones - Título - Texto - Seleccione la fecha - Formato | F3: El usuario debe de validar que el boton para descargar los estados de cuenta este habilitado | G3: - Los diseños deben adaptarse a una versión responsive. | H3: El boton para descargar los estados cuenta debe de funcionae con exito | I3: Todos | M3: Todos | N3: =COUNTIF(I2:I20,"Todos") -> 7
A4: CP03 | B4: Consulta y descarga de extractos (Estados de cuenta) | C4: Estados de Cuenta- Consulta y descarga de extractos | D4: Ingresar al modulo regional con usuario autorizante - Pais SV | E4: Desde la Posición Consolidada se debe de seleccionar el productos que desea desacargar: - Dar clic en el detalle Producto cuenta de Ahorros o corriente - Dar clic en Estados de cuenta - Se debe de validar que permita realizar una descarga de estado de cuenta de los ultimos 6 meses | F4: Al dar clic en consultar se debe de mostrar : Título: Descarga de estados de cuentas Texto: Si la descarga no se da de inmediato, se debe de mosrtar un mensaje que diga "le enviaremos el archivo al buzón.” Seleccione la fecha: colcoar Año y mes a descargar Formato: PDF Descargar: se debe habilitar el boton para descagar únicamente una vez se haya ingresado al menos el periodo de fecha (MM/AAAA) | G4: - Para el estado de cuenta de El Salvador, solo hace la descarga los últimos 6 meses. - Se debe de tomar en cuenta que para El Salvador solo permite la descarga en PDF Y vendrá seleccionado por Default | H4: La descarga se debe de realizar con exito | I4: El Salvador | M4: El Salvador | N4: =COUNTIF(I2:I20,"El Salvador") -> 2
A5: CP04 | B5: Consulta y descarga de extractos (Estados de cuenta) | C5: Estados de Cuenta- Consulta y descarga de extractos | D5: Ingresar al modulo regional con usuario operador - Pais HN | E5: Desde la Posición Consolidada se debe de seleccionar el productos que desea desacargar: - Dar clic en el detalle Producto cuenta de Ahorros o corriente - Dar clic en Estados de cuenta - Se debe de validar que permita realizar una descarga de estado de cuenta de los ultimos 5 años | F5: Al dar clic en consultar se debe de mostrar : Título: Descarga de estados de cuentas Texto: Si la descarga no se da de inmediato, se debe de mostrar un mesaje que diga "le enviaremos el archivo al buzón.” Seleccione la fecha: colcoar Año y mes a descargar Formato: PDF Descargar: se debe de habilitar únicamente una vez se haya ingresado al menos el periodo de fecha (MM/AAAA) | G5: - Para el estado de cuenta de HN solo hace la descarga los últimos 5 años. - Se debe de tomar en cuenta que para Honduras solo permite la descarga en PDF Y vendrá seleccionado por Default | H5: La descarga se debe de realizar con exito | I5: Honduras | M5: Honduras | N5: =COUNTIF(I2:I21,"Honduras") -> 2
A6: CP05 | B6: Consulta y descarga de extractos (Estados de cuenta) | C6: Estados de Cuenta- Consulta y descarga de extractos | D6: Ingresar al modulo regional con usuario consultor - Pais PA | E6: Desde la Posición Consolidada se debe de seleccionar el productos que desea desacargar: - Dar clic en el detalle Producto cuenta de Ahorros o corriente - Dar clic en Estados de cuenta - Se debe de realizar una descarga de estado de cuenta de uno anterior | F6: Al dar clic en consultar y descargar estado de cuenta se debe de mostrar : Título: Descarga de estados de cuentas Texto: Si la descarga no se da de inmediato, se tiene mostrar un mensaje que diga enviaremos el archivo al buzón.” Seleccione la fecha: se coloca el Año y mes a descargar Formato: PDF Descargar: se debe habilitar el boton de descargar únicamente una vez se haya ingresado al menos el periodo de fecha (MM/AAAA) | G6: - Para el estado de cuenta de Panama, hace la descarga de todos los meses del año actual, y año anterior - Se debe de tomar en cuenta que para Panama solo permite la descarga en PDF Y vendrá seleccionado por Default | H6: La descarga se debe de realizar con exito | I6: Panama | M6: Costa Rica | N6: =COUNTIF(I$2:I22,"Costa Rica") -> 2
A7: CP06 | B7: Consulta y descarga de extractos (Estados de cuenta) | C7: Estados de Cuenta- Consulta y descarga de extractos | D7: Ingresar al modulo regional con usuario autorizante- Pais CR | E7: Desde la Posición Consolidada se debe de seleccionar el productos que desea desacargar: - Dar clic en el detalle Producto cuenta de Ahorros o corriente - Dar clic en Estados de cuenta - Se debe de realizar una descarga de estado de cuenta de los ltimos 5 años | F7: Al dar clic en consultar y descargar estado de cuenta se debe de mostrar : Título: Descarga de estados de cuentas Texto: Si la descarga no se da de inmediato, se tiene mostrar un mensaje que diga enviaremos el archivo al buzón.” Seleccione la fecha: se coloca el Año y mes a descargar Formato: PDF Descargar: se debe habilitar el boton de descargar únicamente una vez se haya ingresado al menos el periodo de fecha (MM/AAAA) | G7: - Para el estado de cuenta de Costa Rica, solo hace la descarga los últimos 5 años. - Se debe de tomar en cuenta que para Costa Rica solo permite la descarga en PDF Y vendrá seleccionado por Default | H7: La descarga se debe de realizar con exito | I7: Costa Rica | M7: Panama | N7: =COUNTIF(I$2:I23,"Panama") -> 2
A8: CP07 | B8: Consulta y descarga de extractos (Estados de cuenta) | C8: Estados de Cuenta- Consulta y descarga de extractos | D8: Ingresar al modulo regional con usuario autorizante- Pais COL | E8: Desde la Posición Consolidada se debe de seleccionar el productos que desea desacargar: - Dar clic en el detalle Producto cuenta de Ahorros o corriente - Dar clic en Estados de cuenta - Se debe de realizar una descarga de estado de cuenta de los ltimos 5 años | F8: Al dar clic en consultar y descargar estado de cuenta se debe de mostrar : Título: Descarga de estados de cuentas Texto: Si la descarga no se da de inmediato, se tiene mostrar un mensaje que diga enviaremos el archivo al buzón.” Seleccione la fecha: se coloca el Año y mes a descargar Formato: PDF Descargar: se debe habilitar el boton de descargar únicamente una vez se haya ingresado al menos el periodo de fecha (MM/AAAA) | G8: - Para el estado de cuenta de Colombia, solo hace la descarga los últimos 5 años. - Se debe de tomar en cuenta que para Colombia debe de permitir la descarga en PDF, Excel (.xlsx) , Plano (.txt) | H8: La descarga se debe de realizar con exito | I8: Colombia | M8: Miami | N8: =COUNTIF(I$2:I24,"Miami") -> 2
A9: CP08 | B9: Consulta y descarga de extractos (Estados de cuenta) | C9: Estados de Cuenta- Consulta y descarga de extractos | D9: Ingresar al modulo regional con usuario autorizante- Pais MIA | E9: Desde la Posición Consolidada se debe de seleccionar el productos que desea desacargar: - Dar clic en el detalle Producto cuenta de Ahorros o corriente - Dar clic en Estados de cuenta - Se debe de realizar una descarga de estado de cuenta de los ltimos 12 meses | F9: Al dar clic en consultar y descargar estado de cuenta se debe de mostrar : Título: Descarga de estados de cuentas Texto: Si la descarga no se da de inmediato, se tiene mostrar un mensaje que diga enviaremos el archivo al buzón.” Seleccione la fecha: se coloca el Año y mes a descargar Formato: PDF Descargar: se debe habilitar el boton de descargar únicamente una vez se haya ingresado al menos el periodo de fecha (MM/AAAA) | G9: - Para el estado de cuenta de Miami, solo hace la descarga los últimos 12 meses - Se debe de tomar en cuenta que para Miami solo permite la descarga en PDF Y vendrá seleccionado por Default | H9: La descarga se debe de realizar con exito | I9: Miami | M9: Colombia | N9: =COUNTIF(I$2:I25,"Colombia") -> 2
A10: CP09 | B10: Consulta y descarga de extractos (Estados de cuenta) | C10: Visualización descarga - Consulta y descarga de extractos | D10: Ingresar al modulo regional con usuario Autorizante - y seleccionar todas las sociedades | E10: Existirán dos formas para visualizar el estado de cuenta una vez el usuario de clic a “Generar” esto dependera del tamaño o rangos de fecha solitados | F10: El usuario debe de realizar una descarga de estado de cuenta con un rango de fecha de un mes atras : Si el tamaño del estado de cuenta permite realizar la descarga en línea, este debe ser generado y el canal debe informar: “Descarga exitosa.” | G10: N/A | H10: La descarga se debe de realizar con exito | I10: Todos
A11: CP10 | B11: Consulta y descarga de extractos (Estados de cuenta) | C11: Visualización descarga - Consulta y descarga de extractos | D11: Ingresar al modulo regional con usuario Operador - y seleccionar todas las sociedades | E11: Existirán dos formas para visualizar el estado de cuenta una vez el usuario de clic a “Generar” esto dependera del tamaño o rangos de fecha solitados | F11: El usuario debe de realizar una descarga de estado de cuenta con un rango de fecha de 3 a 4 meses atras : En caso que el archivo no pueda ser generado inmediatamente se debe de enviar un mensaje temporal que informe: “El estado de cuenta se enviará al buzón de notificaciones del Módulo Regional”, una vez el estado de cuenta sea generado el usuario deberá ingresar al módulo de notificaciones para realizar la descarga del mismo. | G11: N/A | H11: La descarga se debe de realizar con exito | I11: Todos
A12: CP11 | B12: Consulta y descarga de extractos (Estados de cuenta) | C12: Visualización descarga - Consulta y descarga de extractos | D12: Ingresar desde un dispositivo con usuario autorizador / Usuario con aprobacion directa - Pais SV | E12: Realizar la descarga desde un dispositivo con visualización responsiva | F12: Validar que el archivo se descarga al dispositivo se visualice de manera nativa según el dispositivo y sistema operativo. | G12: N/A | H12: La descarga se debe de realizar con exito | I12: El Salvador
A13: CP12 | B13: Consulta y descarga de extractos (Estados de cuenta) | C13: Visualización descarga - Consulta y descarga de extractos | D13: Ingresar desde un dispositivo con usuario autorizador / Usuario con aprobacion directa - Pais PA | E13: Realizar la descarga desde un dispositivo con visualización responsiva | F13: Validar que el archivo se descarga al dispositivo se visualice de manera nativa según el dispositivo y sistema operativo. | G13: N/A | H13: La descarga se debe de realizar con exito | I13: Panama
A14: CP13 | B14: Consulta y descarga de extractos (Estados de cuenta) | C14: Visualización descarga - Consulta y descarga de extractos | D14: Ingresar desde un dispositivo con usuario autorizador / Usuario con aprobacion directa - Pais CR | E14: Realizar la descarga desde un dispositivo con visualización responsiva | F14: Validar que el archivo se descarga al dispositivo se visualice de manera nativa según el dispositivo y sistema operativo. | G14: N/A | H14: La descarga se debe de realizar con exito | I14: Costa Rica
A15: CP14 | B15: Consulta y descarga de extractos (Estados de cuenta) | C15: Visualización descarga - Consulta y descarga de extractos | D15: Ingresar desde un dispositivo con usuario autorizador / Usuario con aprobacion directa - Pais HN | E15: Realizar la descarga desde un dispositivo con visualización responsiva | F15: Validar que el archivo se descarga al dispositivo se visualice de manera nativa según el dispositivo y sistema operativo. | G15: N/A | H15: La descarga se debe de realizar con exito | I15: Honduras
A16: CP15 | B16: Consulta y descarga de extractos (Estados de cuenta) | C16: Visualización descarga - Consulta y descarga de extractos | D16: Ingresar desde un dispositivo con usuario autorizador / Usuario con aprobacion directa - Pais COL | E16: Realizar la descarga desde un dispositivo con visualización responsiva | F16: Validar que el archivo se descarga al dispositivo se visualice de manera nativa según el dispositivo y sistema operativo. | G16: N/A | H16: La descarga se debe de realizar con exito | I16: Colombia
A17: CP16 | B17: Consulta y descarga de extractos (Estados de cuenta) | C17: Visualización descarga - Consulta y descarga de extractos | D17: Ingresar desde un dispositivo con usuario autorizador / Usuario con aprobacion directa - Pais MIA | E17: Realizar la descarga desde un dispositivo con visualización responsiva | F17: Validar que el archivo se descarga al dispositivo se visualice de manera nativa según el dispositivo y sistema operativo. | G17: N/A | H17: La descarga se debe de realizar con exito | I17: Miami
A18: CP17 | B18: Consulta y descarga de extractos (Estados de cuenta) | C18: Consulta y descarga de extractos (Estados de cuenta) / Cambio de idioma | D18: El usuario debe de realizar el proceso de cambio de idioma de español a ingles | E18: Se debe de validar que al realizar el cambio de idioma no afecte los productos que se muestran en la pocion consolidada | F18: El usuario debe de consultar los productos, para validar que se muestre de forma correcta en idioma ingles y los textos del canal deben corresponder | G18: N/A | H18: El cambio de idioma se debe de realizar exitosamente | I18: Todos
A19: CP18 | B19: Consulta y descarga de extractos (Estados de cuenta) | C19: Consulta y descarga de extractos (Estados de cuenta) / Cambio de idioma | D19: El usuario debe de realizar el proceso de cambio de idioma de ingles a español | E19: Se debe de validar que al realizar el cambio de idioma no afecte los productos que se muestran en la pocion consolidada | F19: El usuario debe de consultar los productos, para validar que se muestre de forma correcta en idioma español y los textos del canal deben corresponder | G19: N/A | H19: El cambio de idioma se debe de realizar exitosamente | I19: Todos
A20: CP19 | B20: Consulta y descarga de extractos (Estados de cuenta) | C20: Logs | D20: Toda interacción que se realice en el módulo de Transferencias debe quedar almacenada para posterior consulta de los usuarios del control Center con el servicio asignado, quienes podrán consultar y visualizar Logs y descarga de informes del Registro completo de cualquier novedad realizada desde el módulo regional, El sistema debe generar y registrar de forma completa y precisa toda la información relacionados con la creación o cualquier novedad realizada, incluyendo toda la información detallada de los datos de entrada y salida, y cualquier error o excepción que se produzca durante el proceso. | E20: Validar que el usuario BO pueda realizar un filtro de busqueda : Fecha de novedad desde - hasta, País, Tipo de novedad | F20: N/A | G20: N/A | H20: La busqueda de logs debe ser exitosa | I20: Todos

Sheet HU008_PER - Módulo de administr
A1: not | B1: Requerimiento | C1: Título | D1: Precondición | E1: Descripción | F1: Condición | G1: Resultado | H1: Resultado | I1: Preubas en UAT
A2: CP01 | B2: Usuarios Back Office Control Center- Tech | C2: Validación de Perfiles únicamente de Banca en Línea | D2: Usuario BO ingrese al CC de su banca Local SV-CR-PA-HN | E2: Ingresar Credenciales Exitosas-Permite el acceso Ingresar Credenciales Erroneas- No permite el acceso | F2: Se solicita ejecutar pruebas de no afectación con usuarios BO que no poseen perfiles Regionales | G2: Solamente puede visualizar las empresas Local y como lectura un cliente marcado como multilatino | H2: Todos | L2: Consolidado | M2: =COUNTA(H2:H136) -> 135
A3: CP02 | B3: Usuarios Back Office Control Center -Tech | C3: Validación Marcación Segmento Personas | D3: Cliente existente al segmento de personas no debe mostrar nuevos campos (MVP sí mostrará el campo de 'Cliente módulo Regional') Deben poseer información de clientes existentes para cada uno de los segmentos Usuarios BO a utilizar deben de ser Banca en línea de cada uno de los países | E3: Ingresar a CC CR Ingresar al menú de Administración Clientes Seleccionar Clientes Puede Utilizar los filtros de País, Tipo de Documento, Número de Documento, Nombre Empresa Seleccionar Segmento Personas y/o Pyme Seleccionar Buscar debe mostrar el resultado Seleccionar Detalle de cliente a modificar Debe visualizar los botones Volver-Modificar-Eliminar-Deshabilitar Seleccionar Modificar Mostrará el Campo Cliente Multilatino (MVP sí mostrará el campo de 'Cliente módulo Regional') Los botones a visualizar es Volver y Continuar Seleccionar Volver Visualizará la información del detalle | G3: Efectuar los casos de prueba de no afectación para CC de CR de los segmentos | H3: Todos | J3: CR
A4: CP03 | B4: Usuarios Back Office Control Center - Tech Usuario Operador/Autorizante | C4: Validación usuarios con Perfiles Regionales | D4: Cliente ya debe existir en la Banca Local Seleccionar opción de Modificar la sociedad y seleccionar empresa Local como multilatina Solamente el usuario dominio del país podrá marcar el cliente | E4: Utilizar una empresa dentro del listado indicado Ingresar a CC CR- SV- HN- PA Ingresar al menú de Administración Clientes Seleccionar Clientes Puede Utilizar los filtros de País, Tipo de Documento, Número de Documento, Nombre Empresa Seleccionar Buscar debe mostrar el resultado Seleccionar Detalle de la sociedad a modificar Debe visualizar los botones Volver-Modificar-Eliminar-Deshabilitar Seleccionar Modificar Debe mostrarse el Campo Cliente módulo Regional Seleccionar Continuar Seleccionar en Perfiles Continuar Seleccionar en Confirmar Continuar Finalizar el proceso de la modificación del cliente y debe mostrar un mensaje de pendiente de Autorización | G4: Solicitud se encuentre pendienta de Aprobación en Control Center | H4: Todos
A5: CP04 | B5: Usuarios Back Office Control Center - Tech Autorizante | C5: Validar que la solicitud de autorización del mismo dominio se muestre. | D5: El usuario Autorizante debe tener permiso con perfil Autorizante | E5: Ingresar al CC CR Autorizar la solicitud enviada por el Operador BO o por otro usuario Autorizante del mismo dominio país Ingresar al menú Administración Clientes Seleccionar Clientes Puede Utilizar los filtros de País, Tipo de Documento, Número de Documento, Nombre Empresa Seleccionar Buscar debe mostrar el resultado Seleccionar Detalle de la sociedad a modificar Debe visualizar los botones Volver-Modificar-Eliminar-Deshabilitar No se debe seleccionar ningún botón unicamente es validar que los gestiones se visualicen desde ese menú Ingresar al Menú de Autorizaciones Seleccionar Autorizaciones Pendientes Utilizar los filtros de Usuario - Fecha desde -Fecha Hasta Seleccionar la opción Buscar Debe mostrar el resultado de Solicitud Seleccionar detalle del cliente seleccionado Debe mostrar botones : Volver- Autoriza- Rechazar Seleccionar Autorizar Seleccionar Continuar hasta finalizar el proceso y capturar todas las pantallas del proceso | G5: Autorizar la solicitud de modificación de la empresa | H5: Todos | J5: Dependencia de CR
A6: CP05 | B6: Usuarios Back Office Control Center Usuario Operador/Autorizante | C6: Validación usuarios con Perfiles Regionales | D6: Cliente ya debe existir en la Banca Local Seleccionar opción de Modificar la sociedad y seleccionar empresa Local como multilatina Solamente el usuario dominio del país podrá marcar el cliente | E6: Utilizar una empresa dentro del listado indicado Ingresar a CC Bel Local-SV-PA-HN Ingresar al menú de Administración Clientes Seleccionar Clientes Puede Utilizar los filtros de País, Tipo de Documento, Número de Documento, Nombre Empresa Seleccionar Buscar debe mostrar el resultado Seleccionar Detalle de la sociedad a modificar Debe visualizar los botones Volver-Modificar-Eliminar-Deshabilitar Seleccionar Modificar Debe mostrarse el Campo Cliente Módulo Regional Seleccionar Continuar Seleccionar en Perfiles Continuar Seleccionar en Confirmar Continuar Finalizar el proceso de la modificación del cliente y debe mostrar un mensaje de pendiente de Autorización | G6: Solicitud se encuentre pendiente de Aprobación en Control Center | H6: Alcance | J6: -
A7: CP06 | B7: Usuarios Back Office Control Center Autorizante | C7: Validar que la solicitud de autorización del mismo dominio se muestre | D7: El usuario Autorizante debe tener permiso con perfil Autorizante | E7: Ingresar al CC BEL -SV-PA-HN Autorizar la solicitud enviada por el Operador BO o por otro usuario Autorizante del mismo dominio país Ingresar al menú Administración Clientes Seleccionar Clientes Puede Utilizar los filtros de País, Tipo de Documento, Número de Documento, Nombre Empresa Seleccionar Buscar debe mostrar el resultado, ya sea por la información ingresada en los filtros o sino se han utilizado los filtros debe mostrar infromación de todos los clientes Seleccionar Detalle de la sociedad a modificar Debe visualizar los botones Volver-Modificar-Eliminar-Deshabilitar No se debe seleccionar ningún botón unicamente es validar que los gestiones se visualicen desde ese menú Ingresar al Menú de Autorizaciones Seleccionar Autorizaciones Pendientes Utilizar los filtros de Usuario - Fecha desde -Fecha Hasta Seleccionar la opción Buscar Debe mostrar el resultado de Solicitud Seleccionar detalle del cliente seleccionado Debe mostrar botones : Volver- Autoriza- Rechazar Seleccionar Autorizar Seleccionar Continuar hasta finalizar el proceso y capturar todas las pantallas del proceso | G7: Autorizar la solicitud de modificación de la empresa | H7: Todos
A8: CP07 | B8: Usuarios Back Office Control Center - Tech Usuario Operador/Autorizante | C8: Validación usuarios con Perfiles Regionales | D8: Cliente ya debe existir en la Banca Local Seleccionar opción de Modificar la sociedad y seleccionar empresa Local como multilatina Solamente el usuario dominio del país podrá marcar el cliente | E8: Utilizar una empresa dentro del listado indicado Ingresar a CC Local HN-PA-SV Ingresar al menú de Administración Clientes Seleccionar Clientes Puede Utilizar los filtros de País, Tipo de Documento, Número de Documento, Nombre Empresa Seleccionar Buscar debe mostrar el resultado Seleccionar Detalle de la sociedad a modificar Debe visualizar los botones Volver-Modificar-Eliminar-Deshabilitar Seleccionar Modificar Debe mostrarse el Campo Cliente Módulo Regional Seleccionar Continuar Seleccionar en Perfiles Continuar Seleccionar en Confirmar Continuar Finalizar el proceso de la modificación del cliente y debe mostrar un mensaje de pendiente de Autorización | G8: Solicitud se encuentre pendiente de Aprobación en Control Center | H8: Todos
A9: CP08 | B9: Usuarios Back Office Control Center - Tech Autorizante | C9: Rechazar la solicitud de autorización del mismo dominio se muestre | D9: El usuario Autorizante debe tener permiso con perfil Autorizante | E9: Rechazar la solicitud enviada por el Operador BO o por otro usuario Autorizante del mismo dominio país Ingresar a CC Local HN,SV,PA Ingresar al menú Administración Clientes Seleccionar Clientes Puede Utilizar los filtros de País, Tipo de Documento, Número de Documento, Nombre Empresa Seleccionar Buscar debe mostrar el resultado Seleccionar Detalle de la sociedad a modificar Debe visualizar los botones Volver-Modificar-Eliminar-Deshabilitar No se debe seleccionar ningún botón unicamente es validar que los gestiones se visualicen desde ese menú Ingresar al Menú de Autorizaciones Seleccionar Autorizaciones Pendientes Utilizar los filtros de Usuario - Fecha desde -Fecha Hasta Seleccionar la opción Buscar Debe mostrar el resultado de Solicitud Seleccionar detalle del cliente seleccionado Debe mostrar botones : Volver- Autoriza- Rechazar Seleccionar Rechazar Seleccionar Continuar hasta finalizar el proceso y capturar todas las pantallas del proceso | G9: Rechazar la solicitud de modificación de la empresa | H9: Todos
A10: CP09 | B10: Usuarios Back Office Control Center - Tech Usuario Operador/Autorizante | C10: Validar la consulta de un cliente Multilatino de diferente dominio | D10: Seleccionar una empresa previamente marcada como cliente multilatino El usuario de BO debe consultar cliente con dominio diferente a su usuario HN, CR, PA, SV | E10: Utilizar una empresa dentro del listado indicado Ingresar a CC de DvCR Ingresar al menú de Administración Clientes Seleccionar Clientes Puede Utilizar los filtros de País, Tipo de Documento, Número de Documento, Nombre Empresa Seleccionar Buscar debe mostrar el resultado Validar que la empresa este marcado como Cliente Multilatino Debe visualizar el botón de Volver | G10: El usuario solamente podrá realizar consultas no visualizará las modificaciones | H10: Todos | J10: Dependencia de CR
A11: CP10 | B11: Usuarios Back Office Control Center - Tech Usuario Operador/Autorizante | C11: Alta de cliente Nuevo Tipo Multilatino | D11: Cliente No debe existir en la Banca Local No debe estar marcado como cliente Multilatino Utilizar un cliente del listado proporcionado | E11: Utilizar una empresa dentro del listado indicado Ingresar a CC Local COSTA RICA Ingresar al menú de Administración Clientes Seleccionar Clientes Puede Utilizar los filtros de País, Tipo de Documento, Número de Documento, Nombre Empresa Seleccionar Buscar debe mostrar el resultado: La búsqueda no ha obtenido resultados Seleccionar Nuevo Cliente Debe mostrar 2 campos: 1- Cliente Multilatino 2- Cliente Módulo Regional' check box Seleccionar unicamente 'Cliente Módulo Regional' País: Solamente debe mostrar el país dominio del usuario Tipo de Documento: Mostarar el listado de los elementos deben ser solamente del país que indica en el campo País, por ejemplo si se selecciona CR, solamente deben aparecer en el campo tipo de documento: ID persona Física, Dimex, DIDI, Pasaporte Seleccionar Aceptar Continuar con datos Filiatorios Continuar con PERFILES Continuar con Operadores Continuar con Confirmar Finalizar el proceso del Alta | F11: - Permitir marcar al cliente con ambos checks. - Permitir marcar al cliente solo con el campo 'Cliente Multilatino' - Permitir marcar al cliente solo con el campo 'Cliente módulo Regional' | G11: Solicitud se encuentre pendiente de Aprobación en Control Center | H11: Todos | J11: Dependencia de CR
A12: CP11 | B12: Usuarios Back Office Control Center - Tech Usuario Operador/Autorizante | C12: Alta de cliente Nuevo Tipo Multilatino | D12: Cliente No debe existir en la Banca Local No debe estar marcado como cliente Multilatino Utilizar un cliente del listado proporcionado | E12: Utilizar una empresa dentro del listado indicado Ingresar a CC Local COSTA RICA Ingresar al menú de Administración Clientes Seleccionar Clientes Puede Utilizar los filtros de País, Tipo de Documento, Número de Documento, Nombre Empresa Seleccionar Buscar debe mostrar el resultado: La búsqueda no ha obtenido resultados Seleccionar Nuevo Cliente Debe mostrar 2 campos: 1- Cliente Multilatino 2- Cliente Módulo Regional' check box Seleccionar los 2 checks 1- Cliente Multilatino 2- Cliente Módulo Regional' check box No debe mostrar error al momento de confirmar la creación del cliente y getión quedará con estado pendiente de autorización. | F12: - Permitir marcar al cliente con ambos checks. - Cliente podrá acceder a PER TACTICO y ESTRUCTURAL | G12: Solicitud se encuentre pendiente de Aprobación en Control Center | H12: Todos | J12: Dependecia de CR
A13: CP12 | B13: Usuarios Back Office Control Center - Tech Usuario Operador/Autorizante | C13: Alta de cliente Nuevo Tipo Multilatino | D13: Cliente No debe existir en la Banca Local No debe estar marcado como cliente Multilatino Utilizar un cliente del listado proporcionado | E13: Utilizar una empresa dentro del listado indicado Ingresar a CC Local COSTA RICA Ingresar al menú de Administración Clientes Seleccionar Clientes Puede Utilizar los filtros de País, Tipo de Documento, Número de Documento, Nombre Empresa Seleccionar Buscar debe mostrar el resultado: La búsqueda no ha obtenido resultados Seleccionar Nuevo Cliente Debe mostrar 2 campos: 1- Cliente Multilatino 2- Cliente Módulo Regional' check box Seleccionar 1 check 1- Cliente Multilatino No debe mostrar error al momento de confirmar la creación del cliente y getión quedará con estado pendiente de autorización. | F13: - Permitir marcar al cliente solo con el campo 'Cliente Multilatino' - Cliente solo podrá acceder al PER táctico | G13: Solicitud se encuentre pendiente de Aprobación en Control Center | H13: Todos | J13: Dependencia de CR
A14: CP13 | B14: Usuarios Back Office Control Center - Tech Usuario Operador/Autorizante | C14: Alta de cliente Nuevo Tipo Multilatino | D14: Cliente No debe existir en la Banca Local No debe estar marcado como cliente Multilatino Utilizar un cliente del listado proporcionado | E14: Utilizar una empresa dentro del listado indicado Ingresar a CC Local COSTA RICA Ingresar al menú de Administración Clientes Seleccionar Clientes Puede Utilizar los filtros de País, Tipo de Documento, Número de Documento, Nombre Empresa Seleccionar Buscar debe mostrar el resultado: La búsqueda no ha obtenido resultados Seleccionar Nuevo Cliente Debe mostrar 2 campos: 1- Cliente Multilatino 2- Cliente Módulo Regional' check box Seleccionar 1 check 2- Cliente Módulo Regional' check box No debe mostrar error al momento de confirmar la creación del cliente y getión quedará con estado pendiente de autorización. | F14: - Permitir marcar al cliente solo con el campo 'Cliente módulo Regional' - CLiente solo podrá acceder al PER ESTRUCTURAL | G14: Solicitud se encuentre pendiente de Aprobación en Control Center | H14: Todos | J14: Dependencia de CR
A15: CP14 | B15: Usuarios Back Office Control Center - Tech Autorizante | C15: Validar que la solicitud de autorización del mismo dominio se muestre para el Alta | D15: El usuario Autorizante debe tener permiso con perfil Autorizante | E15: Ingresar al CC BEl Local- COSTA RICA Autorizar la solicitud enviada por el Operador BO o por otro usuario Autorizante del mismo dominio país Ingresar al menú Administración Clientes Seleccionar Clientes Puede Utilizar los filtros de País, Tipo de Documento, Número de Documento, Nombre Empresa Seleccionar Buscar debe mostrar el resultado Seleccionar Detalle de la sociedad a modificar Debe visualizar los botones Volver-Modificar-Eliminar-Deshabilitar No se debe seleccionar ningún botón unicamente es validar que las gestiones se visualicen desde ese menú Ingresar al Menú de Autorizaciones Seleccionar Autorizaciones Pendientes Utilizar los filtros de Usuario - Fecha desde -Fecha Hasta Seleccionar la opción Buscar Debe mostrar el resultado de Solicitud Seleccionar detalle del cliente seleccionado Debe mostrar botones : Volver- Autoriza- Rechazar Seleccionar Autorizar Seleccionar Continuar hasta finalizar el proceso y capturar todas las pantallas del proceso | G15: Autorizar la solicitud de Alta del nuevo cliente | H15: Todos | J15: Dependencia de CR
A16: CP15 | B16: Usuarios Back Office Control Center - Tech Usuario Operador/Autorizante | C16: Modificación de cliente multilatino | D16: Cliente debe existir en la banca local de CR y estar marcado como 'Multilatino' | E16: Utilizar una empresa dentro del listado indicado Ingresar a CC Local COSTA RICA Ingresar al menú de Administración Clientes Seleccionar Clientes Puede Utilizar los filtros de País, Tipo de Documento, Número de Documento, Nombre Empresa Seleccionar Buscar debe mostrar el resultado: La búsqueda no ha obtenido resultados Ingresar al detalle del cliente y hacer clic en modificar Debe mostrar 2 campos: 1- Cliente Multilatino (Previamente marcado) 2- Cliente Módulo Regional' check box (Seleccionar campo nuevo) No debe mostrar error al momento de confirmar la modificación del cliente y getión quedará con estado pendiente de autorización. | F16: - Permitir marcar al cliente con ambos checks. AL cumplir el esquema de autorización debe permitir lo siguiente: - Cliente podrá acceder a PER TACTICO y ESTRUCTURAL | G16: Solicitud se encuentre pendiente de Aprobación en Control Center | H16: Todos | J16: Dependecia de CR
A17: CP16 | B17: Usuarios Back Office Control Center - Tech Usuario Operador/Autorizante | C17: Modificación de cliente multilatino | D17: Cliente debe existir en la banca local de CR y estar marcado como 'Multilatino' | E17: Utilizar una empresa dentro del listado indicado Ingresar a CC Local COSTA RICA Ingresar al menú de Administración Clientes Seleccionar Clientes Puede Utilizar los filtros de País, Tipo de Documento, Número de Documento, Nombre Empresa Seleccionar Buscar debe mostrar el resultado: La búsqueda no ha obtenido resultados Ingresar al detalle del cliente y hacer clic en modificar Debe mostrar 2 campos: 1- Cliente Multilatino (Previamente marcado) 2- Cliente Módulo Regional' check box Usuario BO desmarque el check de cliente multilatino y marque unicamente el check de Cliente Módulo Regional No debe mostrar error al momento de confirmar la modificación del cliente y getión quedará con estado pendiente de autorización. | F17: - Permitir marcar al cliente con el check de 'Cliente Módulo Regional' AL cumplir el esquema de autorización debe permitir lo siguiente: - Cliente podrá acceder a PER ESTRUCTURAL | G17: Solicitud se encuentre pendiente de Aprobación en Control Center | H17: Todos | J17: Dependencia de CR
A18: CP17 | B18: Usuarios Back Office Control Center - Tech Usuario Operador/Autorizante | C18: Modificación de cliente multilatino | D18: Cliente debe existir en la banca local de CR y estar marcado como 'Cliente Módulo Regional | E18: Utilizar una empresa dentro del listado indicado Ingresar a CC Local COSTA RICA Ingresar al menú de Administración Clientes Seleccionar Clientes Puede Utilizar los filtros de País, Tipo de Documento, Número de Documento, Nombre Empresa Seleccionar Buscar debe mostrar el resultado: La búsqueda no ha obtenido resultados Ingresar al detalle del cliente y hacer clic en modificar Debe mostrar 2 campos: 1- Cliente Multilatino 2- Cliente Módulo Regional' check box (Previamente marcado) Usuario BO desmarque el check de cliente Módulo regional y marque unicamente el check de Cliente Multilatino No debe mostrar error al momento de confirmar la modificación del cliente y getión quedará con estado pendiente de autorización. | F18: - Permitir marcar al cliente con el check de 'Cliente Multilatino' AL cumplir el esquema de autorización debe permitir lo siguiente: - Cliente podrá acceder a PER Táctico | G18: Solicitud se encuentre pendiente de Aprobación en Control Center | H18: Todos | J18: Dependencia de CR
A19: CP18 | B19: Usuarios Back Office Control Center - Tech Autorizante | C19: Rechazar la solicitud de autorización del mismo dominio se muestre | D19: El usuario Autorizante debe tener permiso con perfil Autorizante | E19: Rechazar la solicitud enviada por el Operador BO o por otro usuario Autorizante del mismo dominio país Ingresar a CC Local HN,SV,PA Ingresar al menú Administración Clientes Seleccionar Clientes Puede Utilizar los filtros de País, Tipo de Documento, Número de Documento, Nombre Empresa Seleccionar Buscar debe mostrar el resultado Seleccionar Detalle de la sociedad a modificar Debe visualizar los botones Volver-Modificar-Eliminar-Deshabilitar No se debe seleccionar ningún botón unicamente es validar que los gestiones se visualicen desde ese menú Ingresar al Menú de Autorizaciones Seleccionar Autorizaciones Pendientes Utilizar los filtros de Usuario - Fecha desde -Fecha Hasta Seleccionar la opción Buscar Debe mostrar el resultado de Solicitud Seleccionar detalle del cliente seleccionado Debe mostrar botones : Volver- Autoriza- Rechazar Seleccionar Rechazar Seleccionar Continuar hasta finalizar el proceso y capturar todas las pantallas del proceso | F19: - Permitir marcar al cliente con el check de 'Cliente Módulo Regional' AL cumplir el esquema de autorización debe permitir lo siguiente: - Cliente podrá acceder a PER ESTRUCTURAL | G19: Rechazar la solicitud de modificación de la empresa | H19: Todos
A20: CP19 | B20: Usuarios Back Office Control Center - Tech Usuario Operador/Autorizante | C20: Validación usuarios con Perfiles Regionales | D20: Cliente debe existir en la banca local CR-SV-HN y PA y estar marcado como 'Cliente Módulo Regional | E20: Utilizar una empresa dentro del listado indicado Ingresar a CC Local HN-PA-SV Validar el detalle del cliente que se encuentre marcado como Cliente Módulo Regional y seleccionar Ingresar a los usuarios y validar que se encuentren expuestos para PER ESTRUCTURAL | F20: -Cliente debe estar marcado como 'Cliente Módulo Regional' | G20: Solicitud se encuentre pendiente de Aprobación en Control Center | H20: Todos
A21: CP20 | B21: Usuarios Back Office escala 7/24 | C21: Validación de Perfiles de usuarios BO regionales | D21: Usuario BO PER ingrese a CC de la banca local de SV, CR, HN, PA | E21: Ingresar Credenciales de usuario BO regionales | F21: Se solicita ejecutar pruebas de no afectación con usuarios BO que poseen perfiles regionales | G21: No permita el ingreso | H21: Todos
A22: CP21 | B22: Usuarios Back Office escala 7/24 | C22: Validación de Perfiles de usuarios BO regionales | D22: Envío de contraseña al correo del usuario BO del nuevo CC | E22: Ingresar Credenciales de usuario BO regionales en el nuevo CC | G22: Ingreso exitoso | H22: Todos
A23: CP22 | B23: Usuarios Back Office escala 7/24 | C23: Validación de Perfiles de usuarios BO regionales | D23: Envío de contraseña al correo del usuario BO del nuevo CC | E23: Ingresar Credenciales incorrectas de usuario BO regionales | G23: No permita el ingreso | H23: Todos
A24: CP23 | B24: Perfilamiento Usuarios BO | C24: Asignación de perfiles a usuarios BO preparador | E24: Se deben asignar las siguientes opciones de menú al usuario Preparador: 1- Operador Cliente: Mantenimiento de Operadores permite modificar a usuarios dentro del canal dar alta, inactivar, eliminar y realizar consultas. 2- Perfiles Cliente : Permisos asignados a clientes empresas asignación de funcionalidades Mantenimiento de Usuarios y Empresa 3- Consultas 4- Transaccionales 5- Administrador clientes 6- consulta transacciones 7- Módulo | G24: Usuario BO preparador solo podrá visualizar e ingresar a las opciones de menú asignadas | H24: Todos | J24: Pausado
A25: CP24 | B25: Asignación de perfiles a usuarios BO Autorizador. | C25: Asignación de perfiles a usuarios BO autorizador | E25: Se deben asignar las siguientes opciones de menú al usuario Autorizador: 1- Operador Cliente: Mantenimiento de Operadores permite modificar a usuarios dentro del canal dar alta, inactivar, eliminar y realizar consultas. 2- Perfiles Cliente : Permisos asignados a clientes empresas asignación de funcionalidades Mantenimiento de Usuarios y Empresa 3- Consultas 4- Transaccionales 5- Administrador clientes 6- consulta transacciones 7- Módulo 8- autorización 9- Autorizaciones | G25: Usuario BO autorizador solo podrá visualizar e ingresar a las opciones de menú asignadas | H25: Todos | J25: Pausado
A26: CP25 | B26: Perfilamiento Usuarios BO | C26: Asignación de perfiles a Super usuarios BO | E26: Se deben asignar las siguientes opciones de menú a Super Usuarios: Administración Central Configuración Operador Cliente: Mantenimiento de Operadores permite modificar a usuarios dentro del canal dar alta, inactivar, eliminar y realizar consultas. Mantenimiento de usuarios Bancos : Creación de usuarios Internos Bancos dependiendo del perfil, Gestión Perfiles Cliente : Permisos asignados a clientes empresas asignación de funcionalidades Mantenimiento de Usuarios y Empresas Autorización Consulta Transaccionales Perfiles Operador Banco Permisos asignados a usuarios internos asignación de módulos. Administración Clientes Clientes Consulta transacciones Esquema de Firmas -Autorizaciones Operadores Perfiles Permisos producto Personas Producto Autorizaciones Autorizaciones Pendientes Configuración Clasificación Producto Funcionalidades Matrices Permiso Parámetro General Segmento Módulo Enumerados de errores Módulos Trace-Visualizador Centro de Recibos Elementos Mensajes CMM Template Ticket Enumerados Carga Masiva por Archivo Carga Masiva consulta Conjunto de Enumerados Enumerados Simples Errores Perfiles Usuario Banco | G26: Super usuario BO podrá tener acceso a todas las opciones del menú de CC | H26: Todos | J26: Pausado
A27: CP26 | B27: Gestión cliente CC Escala 7/24 | C27: Control dual de gestiones | E27: Todas las gestiones de todos los usuarios, preparadores, autorizantes y super usuarios quedarán pendientes de autorización. | G27: Gestiones requerirán de una segunda autorización, por usuarios autorizantes y super usuarios. | H27: Todos | J27: Escala 7/24
A28: CP27 | B28: Usuarios Back Office escala 7/24 | C28: Visualización del header de CC | D28: Crear el header para el nuevo control center que permita visualizar al usuario conectado la información en la parte superior de la pantalla | E28: El header debe mostrar los siguiemtes campos: Usuario conectado: Se debe presentar de manera fija el nombre del usuario que se encuentra conectado en la parte superior. País Usuario: Se debe presentar de manera fija al lado del nombre del usuario la bandera del país al cual pertenece el usuario con la iniciales del país. podrá ser una de las siguientes opciones (COL - PA - CR - HN - SLV - MIA) Último acceso: Se debe presentar de manera fija la fecha del último acceso que tuvo el usuario presentando en formato dd/mm/aaaa seguido de la hora así: hh/mm/ss. Cierre de Sesión: Se debe presentar botón que permita al usuario finalizar la sesión de manera voluntaria, la sesión por inactividad se finalizará a los 10 min el cual podrá ser parametrizable. | G28: Visualizar el header con la información del usuario | H28: Todos
A29: CP28 | B29: Usuarios Back Office escala 7/24 | C29: Visualización del menú vertical izquierdo (Sidebar) | D29: Acceso al menú vertical izquierdo | E29: En el Menú vertical izquierdo deberá visualizar las siguientes opciones de acuerdo al rol asignado al usuario Inicio: habilitado a todos los usuarios, al dar clic debe llevar al usuario al inicio del Dashboard. Administración: Módulo visible para todos los usuarios, permite crear, consultar, editar y agregar empresas a los grupos regionales creados. (las opciones de crear, editar y adicionar empresas únicamente serán visibles para los usuarios con perfil preparador) Adicional permite consultar Grupos de productos asignados, usuarios y esquemas de firmas dentro del canal. Aprobación: Módulo visible únicamente para usuarios con perfil “Aprobador” o “Super Usuario” permite filtrar, visualizar, aprobar o eliminar las novedades enviadas por los usuarios con perfil preparador. Log Auditoría: Módulo visible para todos los usuarios, quienes podrán consultar y visualizar Logs del Registro completo de cualquier novedad realizada desde el control Center y en el Front de los usuarios. Transacciones: Módulo visible para todos los usuarios, permite realizar consultas de procesos ejecutados por los usuarios en el front del canal. Banner: Módulo visible únicamente para rol super usuario, permite administrar banners publicitarios dentro del canal. Administración central: Módulo visible únicamente para rol super usuarios, quienes podran crear, modificar, eliminar usuarios BO | G29: Visualizar y acceder al sidebar según los permisos de cada usuario | H29: Todos
A30: CP29 | B30: Usuarios Back Office escala 7/24 | C30: Visualización del menú vertical izquierdo (Sidebar) | D30: Acceso al Módulo de administración / Grupo Regionales | E30: Debe permitir a todos los usuario BO: Crear clientes Consultar clientes Editar clientes Agregar empresas a los grupos de productos. | G30: Gestionar grupos regionales de forma exitosa | H30: Todos
A31: CP30 | B31: Usuarios Back Office escala 7/24 | C31: Visualización del menú vertical izquierdo (Sidebar) | D31: Acceso al Módulo de administración / Grupo Regionales | E31: Este submódulo se divide en consultas y creación | G31: Mostrar submódulos de consulta y creación | H31: Todos
A32: CP31 | B32: Usuarios Back Office escala 7/24 | C32: Visualización del menú vertical izquierdo (Sidebar) | D32: Acceso al Módulo de administración / Grupo Regionales | E32: Al ingresar al menú de consultas debe mostrar los siguientes campos: Fecha creación: se debe mostrar la fecha en la que se creó el grupo regional. Casa Matriz: Se debe presentar el nombre y bandera del país al que corresponde la casa matriz. Nombre de Grupo Regional: Se debe presentar el Nombre con el que se creó el Grupo. Empresa: Campo alfanumérico y permita consultar con el nombre del cliente País: Mostrar el lista Colombia, Costa Rica, El Salvador, Honduras, Miami y Panamá, será parametrizable Quick Action: Al dar clic muestra las siguientes opciones. Ver detalle: Al dar clic debe actualizar la pantalla y permite visualizar cómo fue creado un Grupo. Eliminar: únicamente visible para usuarios preparadores con el dominio propio del país sobre el que realiza la novedad. Filtros: Debe tener una opción que permita realizar filtros de acuerdo a los títulos de resultados. Ordenar: Debe tener un elemento que permite ordenar la información dando clic de manera intuitiva en los títulos de las columnas de mayor a menor y de menor a mayor. Paginación: Se debe mostrar 50 resultados por página. Descargar: Debe tener un elemento que permita realizar la descarga en Excel y PDF Botón de regresar: Redirigir a la pantalla anterior. Este módulo dependerá del perfilamiento del usuario utilizado , manteniendo la regla que únicamente los usuarios dominio de cada país, otro usuario ajeno al dominio únicamente tendrá acceso a consulta y solo se le presentará el botón de Regresar | G32: Visualización de registros de clientes | H32: Todos
A33: CP32 | B33: Usuarios Back Office escala 7/24 | C33: Visualización del menú vertical izquierdo (Sidebar) | D33: Acceso al Módulo de administración / Empresas | E33: Permitir consultar empresas que se encuentran asociadas a algún grupo regional, la consulta se puede aplicar filtros, ordenar la información y descargar reportes Resultado Consulta: Fecha asociación: Se debe mostrar la fecha en la que se ligó una sociedad al grupo regional. País: Se mostrará la bandera y las iniciales del país al cual pertenece la empresa. Empresa: se mostrará el nombre de la razón social tal y cómo se encuentra creada en el core del país. Tipo de identificación: Se mostrará el tipo de ID tal cual cómo fue creado en el país origen. incluir mascara. Número de Identificación: el canal debe mostrar el mismo número con el que fue creado en el país origen. Nombre Grupo Regional: el Canal debe mostrar el nombre del grupo regional al que se encuentra asociada. Estado: Se debe visualizar el estado de la sociedad podrá ser: Activo Activo Pen.Inactivación Activo Pen.Eliminación Alra Pend. Autorización Modi.Pend. Autorización Inactivo Pend. Habilitación Inactivo Quick Action: tendrá el accionable de “Ver Detalle” que permitirá actualizar la pantalla mostrando mayor detalle de la empresa y grupo regional al cual pertenece. Los resultados se deben visualizar del más reciente al más antiguo. Filtros: Debe tener una opción que permita realizar filtros de acuerdo a los títulos de resultados. Buscar: Debe existir un elemento que le permita al usuario buscar una empresa escribiendo el nombre de la misma el canal debe validar la información y actualizar la pantalla según el resultado. Ordenar: Debe tener un elemento que permite ordenar la información dando clic de manera intuitiva en los títulos de las columnas de mayor a menor y de menor a mayor. Paginación: Se debe mostrar 50 resultados por página. Descargar: Debe existir un elemento que le permita al usuario realizar la descarga de todas las empresas asociadas en el canal, el usuario al dar clic actualiza la pantalla y el canal muestra: Titulo: Descargar Reporte elemento de cerrar. Texto: Elija el formato Excel (.xlsx) PDF (.pdf) Una vez el cliente seleccione un formato se habilita el botón de “Descargar”. La información descargada debe coincidir si fue aplicado un filtro. El archivo descargado debe contener la información del total de resultados de todas las páginas que se muestran en el resultado. En el formato en PDF en canal debe mostrar el Nombre del banco en la parte superior y el contenido de la consulta en la parte inferior de manera ordenada y clara. | G33: Visualización de registros de clientes | H33: Todos
A34: CP33 | B34: Usuarios Back Office escala 7/24 | C34: Visualización del menú vertical izquierdo (Sidebar) | D34: Acceso al Módulo de administración / Grupo de Productos | E34: Al ingresar a Grupos de Productos, mostrará el usuario se encuentra en una opción donde puede consultar o crear grupos: Resultado consultas: Se debe presentar la siguiente información de resultado por registro. Grupo Regional: Se debe mostrar el nombre del Grupo Regional al que pertenece el Grupo de productos Nombre del grupo: Se debe mostrar el nombre con el que se creó grupo ejemplo: “Tesorería Honduras”. País: El canal debe mostrar las banderas de los productos que se encuentran incluidos en el grupo. Empresas: Se deben visualizar el número del total de las empresas de los productos que se encuentran incluidos en el grupo de productos. Destacado: Debe existir un elemento que permita a los usuarios marcar o desmarcar un grupo como “destacado”, los grupos marcados como destacado serán mostrados en la tarde superior de resultado de las pantallas donde aplique la selección de grupos de productos. Accionables: permite al usuario seleccionar si requiere ver un mayor detalle o eliminar un grupo de productos creado previamente. Adicional esta pantalla permite aplicar: Filtros: Debe tener una opción que permita realizar filtros de acuerdo a los títulos de resultados. Buscar: Debe existir un elemento que le permita al usuario buscar una grupo de productos escribiendo el nombre de la misma el canal debe validar la información y actualizar la pantalla según el resultado. Ordenar: Debe tener un elemento que permite ordenar la información dando clic de manera intuitiva en los títulos de las columnas de mayor a menor y de menor a mayor. Paginación: Se debe mostrar 50 resultados por página. Descargar: Debe existir un elemento que le permita al usuario realizar la descarga de todos los grupos de producto asociados en el canal, el usuario al dar clic actualiza la pantalla y el canal muestra el formato en que se puede descargar Excel (.xlsx) | G34: Visualización de registros de clientes | H34: Todos
A35: CP34 | B35: Usuarios Back Office escala 7/24 | C35: Visualización del menú vertical izquierdo (Sidebar) | D35: Acceso al Módulo de administración / Grupo de Productos - Ver detalle | E35: Detalle Grupo de productos: Debe contar con una opción que permita visualizar mayor detalle y acceder a otras funcionalidades, al dar clic en esta opción se debe visualizar de manera detallada el resumen del grupo de producto seleccionado así: Grupo Regional Nombre del Grupo Países Empresas: Número del total de empresas que conforman el grupo Productos: Número del total de productos seleccionados Tipo Productos Productos Seleccionados: En la pantalla el canal mostrará la información de los productos seleccionados en el mismo orden del paso anterior agrupando la información por tipo de productos. País Empresa Nombre del producto Tipo de Producto Número del Producto Elemento para Descargar Características: Esta opción únicamente es habilitada a todos los usuarios que puedan acceder al control center usuarios que tengan el rol de super usuario, esta opción de Grupo de productos debe permitir visualizar y realizar novedades como creación, edición, eliminación y consulta de grupos de productos teniendo en cuenta las reglas definidas en la historia de usuario. | G35: Visualización de los grupos de productos | H35: Todos
A36: CP35 | B36: Usuarios Back Office escala 7/24 | C36: Visualización del menú vertical izquierdo (Sidebar) Gestión consulta Usuarios canal | D36: Acceso al Módulo de administración / Usuario | E36: La ruta para ingresar es por Administración/usuarios, una vez el usuario de clic se actualiza la pantalla donde permite visualizar los usuarios que pueden acceder al módulo regional, adicional el usuario podrá habilitar un usuarios, ver, eliminar y editar información de usuarios con el mismo dominio de mi país. Resultado consulta: Se debe presentar la siguiente información de resultado por registro. País: El canal debe mostrar la bandera del país origen por el cual accede desde la banca local al módulo regional. Nombre de usuario: Se debe mostrar el nombre del usuario igual a cómo fue creado. Tipo de Identificación: se deben visualizar el nombre del tipo de identificación con el que ingresa a la banca local. Identificación: se deben visualizar el nombre del tipo de identificación con el que ingresa a la banca local. Nombre Grupo Regional: Se debe mostrar el nombre del grupo regional al que se encuentra asociado el usuario. Estado: El canal debe mostrar el estado del usuario en el sistema “Activo” e “Inactivo” serán las dos opciones. Quick Action: El canal debe habilitar los siguientes accionables: Ver detalle: Al dar clic debe actualizar la pantalla y permite visualizar cómo fue creado un usuario Eliminar: únicamente visible para usuarios preparadores de país dominio. | G36: Visualización de registros de usuarios marcados como multilatinos | H36: Todos
A37: CP36 | B37: Usuarios Back Office escala 7/24 | C37: Visualización del menú vertical izquierdo (Sidebar) Gestión consulta Usuarios canal | D37: Acceso al Módulo de administración / Usuario | E37: Adicional permite aplicar las siguientes opciones: Filtros: Debe tener una opción que permita realizar filtros de acuerdo a los títulos de resultados. Buscar: Debe existir un elemento que le permita al usuario buscar un usuario escribiendo el nombre del mismo el canal debe validar la información y actualizar la pantalla según el resultado. Ordenar: Debe tener un elemento que permite ordenar la información dando clic de manera intuitiva en los títulos de las columnas de mayor a menor y de menor a mayor. Paginación: Se debe mostrar 50 resultados por página. Descargar: Debe tener un elemento que permita realizar la descarga en Excel. | G37: Visualización de registros de usuarios marcados como multilatinos | H37: Todos
A38: CP37 | B38: Usuarios Back Office escala 7/24 | C38: Visualización del menú vertical izquierdo (Sidebar) Gestión consulta Usuarios canal | D38: Acceso al Módulo de administración / Usuario | E38: Ver detalle Usuario: Al dar clic sobre el resultado debe permitir visualizar una nueva pantalla que presenta la información del usuario, debe mostrar el grupo empresarial al que pertenece, Nombre del usuario, País origen con la bandera, tipo de identificación y número de identificación, teléfono, Estado del usuario (permite editar si corresponde al país dominio). y posterior detalle de transacciones permitidas y Grupos de productos. Editar: Si el usuario pertenece al país dominio se habilita esta opción, permite editar los Grupos y roles del mismo. Descargar: Esta opción permite realizar la descarga del usuario. previamente el usuario debe seleccionar el tipo de formato. Eliminar: Si el usuario pertenece al país dominio se habilita esta opción. Regresar: Al dar clic lleva a la pantalla anterior. Características: El acceso al submódulo de “usuarios” es habilitada a todos los roles del control center, en el detalle de un Grupo regional debe tener un elemento que permita realizar la creación de un grupo de un usuario desde el Control Center Regional, el detalle de la creación debe ser realizada igual que la asignación desde front. La opción de crear se habilita únicamente sobre usuarios del país dominio del usuario siguiendo la lógica de que solo los usuarios con el rol de preparar visualizan la opción de “crear”. | G38: Visualización de registros de usuarios marcados como multilatinos | H38: Todos
A39: CP38 | B39: Usuarios Back Office escala 7/24 | C39: Visualización del menú vertical izquierdo (Sidebar) Gestión creación Usuarios canal Acceso al Módulo de administración / Usuario | D39: Usuario debe estar previamente marcado como multilatino en CC de la banca local o portal empresarial en Colombia | E39: Mostrar los siguientes campos al momento de adicionar un usuario nuevo: Datos de Usuario: Se habilita la opción para que el usuario administrador busque el usuario que requiere dar acceso al módulo regional, posterior se debe habilitar la siguiente información para buscar los usuarios: País: lista desplegable Tipo Id: lista desplegable, en el cual se debe incluir todos los tipo de identificación que existan en las bancas locales de los países donde banco Davivienda tiene presencia. Número documento: Campo alfanumérico Una vez diligenciados se habilita el botón de “Continuar”. El Módulo regional debe comunicarse con las bancas locales y buscar coincidencias de acuerdo con la información ingresada. | G39: Visualización de campos y selección de información del usuario a buscar. | H39: Todos
A40: CP39 | B40: Usuarios Back Office escala 7/24 | C40: Visualización del menú vertical izquierdo (Sidebar) Gestión creación Usuarios canal Acceso al Módulo de administración / Usuario | D40: Usuario debe estar previamente marcado como multilatino en CC de la banca local o portal empresarial en Colombia | E40: Si al ingresar la información del usuario encuentra coincidencia, mostrará la información en formato lectura no editable. Nombre y apellidos País Tipo de documento Número de identificación Teléfono de contacto Si el usuario a crear ya tiene acceso a la banca en línea en CAM o a los portales en Colombia, según el país seleccionado, el usuario heredará las credenciales del país seleccionado. | G40: Visualización del usuario en formato lectura. | H40: Todos
A41: CP40 | B41: Usuarios Back Office escala 7/24 | C41: Visualización del menú vertical izquierdo (Sidebar) Gestión creación Usuarios canal Acceso al Módulo de administración / Usuario | D41: Usuario debe estar previamente marcado como multilatino en CC de la banca local o portal empresarial en Colombia | E41: Si el usuario a crear no ha sido previamente marcado en CC de la banca local, no mostrará información del usuario y mostrará mensaje en pantalla indicado que el usuario no existe. | F41: - No permitir continuar al siguiente paso | G41: Mostrar mensaje informativo, indicando que el usuario no se encuentra marcado como multilatino | H41: Todos
A42: CP41 | B42: Usuarios Back Office escala 7/24 | C42: Visualización del menú vertical izquierdo (Sidebar) Gestión creación Usuarios canal Acceso al Módulo de administración / Usuario | D42: Usuario debe estar previamente marcado como multilatino en CC de la banca local o portal empresarial en Colombia | E42: Usuario ingrese ID de usuario a crear incorrecto o no existente en la BEL local, mostrará mensaje de error indicando que el ID es incorrecto o no existe y no mostrará detalle de la información. | G42: Mostrar mensaje informativo, indicando que el usuario no existe. | H42: Todos
A43: CP42 | B43: Usuarios Back Office escala 7/24 | C43: Visualización del menú vertical izquierdo (Sidebar) Gestión modificación Usuarios canal | D43: Usuario debe estar previamente marcado como multilatino en CC de la banca local | E43: Si el usuario pertenece al país dominio se habilita esta opción, permite editar los Grupos y roles del mismo. | G43: Visualización y acceso al ícono de modificar (lápiz) | H43: Todos
A44: CP43 | B44: Usuarios Back Office escala 7/24 | C44: Visualización del menú vertical izquierdo (Sidebar) Gestión eliminación Usuarios canal | D44: Usuario debe estar previamente marcado como multilatino en CC de la banca local | E44: Si el usuario pertenece al país dominio se habilita la opción de eliminar. | G44: Visualización y acceso al ícono de eliminar (basurero) | H44: Todos
A45: CP44 | B45: Usuarios Back Office escala 7/24 | C45: Visualización del menú vertical izquierdo (Sidebar) | D45: Acceso al Módulo de administración / Esquema de firmas | E45: Una vez el usuario da clic a Administración / Esquema de firmas, la pantalla debe actualizar y mostrar que el usuario se encuentra en una opción donde puede consultar o crear esquemas: Puede crear, editar y eliminar los esquemas de firmas que aprobarán o rechazarán las operaciones del canal. Para facilitar su gestión, puede usar el buscasdor o los filtros presentados. Botón: Crear Esquema Resultado consultas: Se debe presentar la siguiente información de resultado por registro. Fecha de creación: El canal debe mostrar la fecha en la que fue creado el esquema de firma.. Nombre del esquema: Se debe mostrar el nombre igual a cómo fue creado. Nombre del Grupo: El canal debe mostrar el nombre del grupo al que pertenece el esquema. Estado: se deben visualizar el estado del esquema (Activo - Pendiente - Inconsistencia) Quick Action: Se debe presentar el icono que haga referencia a que se puede eliminar un esquema de firma. Adicional permite aplicar las siguientes opciones: Filtros: Debe tener una opción que permita realizar filtros de acuerdo a los títulos de resultados. Buscar: Debe existir un elemento que le permita al usuario buscar un esquema escribiendo el nombre del mismo, el canal debe validar la información y actualizar la pantalla según el resultado. Ordenar: Debe tener un elemento que permite ordenar la información dando clic de manera intuitiva en los títulos de las columnas de mayor a menor y de menor a mayor. Paginación: Se debe mostrar 50 resultados por página. Descargar: Debe existir un elemento que le permita al usuario realizar la descarga de todos los esquemas en formato Excel (.xlsx) | G45: Visualización de registros de esquema de firmas | H45: Todos
A46: CP45 | B46: Usuarios Back Office escala 7/24 | C46: Visualización del menú vertical izquierdo (Sidebar) | D46: Acceso al Módulo de administración / Esquema de firmas | E46: Detalle esquema de firmas: Al dar clic sobre el registro en la consulta de esquemas de firmas permite tener la misma visual de cómo fue creado el esquema, la información que se visualiza será: Nombre del esquema Niveles de Aprobación: Transacciones y Límites: Grupo de Productos: Opciones Pantalla: Regresar: Al dar clic lleva al usuario a la pantalla anterior. Editar: Permite editar la información de un esquema. Eliminar: Se habilita únicamente a usuarios con rol preparador. Descargar: Permite descargar como fue creado el esquema de firmas. Características: Esta opción únicamente es Habilitada a todos los usuarios debe tener un elemento que permita visualizar los esquemas de firmas asignados a un grupo regional, adicional debe tener un elemento que permita realizar la creación de un grupo de productos desde el Control Center Regional, el detalle de la creación debe ser realizada igual que la asignación desde front siguiendo lo descrito en la H.U. Esquema de firmas | G46: Visualización de registros de esquema de firmas | H46: Todos
A47: CP46 | B47: Usuarios Back Office escala 7/24 | C47: Creación de esquema de firmas | D47: Acceso al Módulo de administración / Esquema de firmas | E47: En la parte superior derecha de la pantalla debe mostrar el botón de 'Crear esquema' - Al hacer clic en el botón 'Crear esquema' deberá redirigir a la pantalla para crear el esquema de firmas. | G47: Visualización y acceso al botón de 'Crear esquema' | H47: Todos
A48: CP47 | B48: Usuarios Back Office escala 7/24 | C48: Visualización del menú vertical izquierdo (Sidebar) | D48: Acceso al Módulo de administración / Módulo de autorizaciones | E48: Detalle: Al dar clic debe actualizar la pantalla y tener una visual de completa de cómo fue enviada la solicitud por el usuario preparador, adicional debe tener los siguientes accionables: Regresar: Al dar clic el usuario vuelve a la pantalla anterior. Aprobar: Al dar clic la solicitud queda Autorizada. Rechazar: Al dar clic la solicitud queda rechazada. Filtros: Debe tener una opción que permita realizar filtros de acuerdo a los títulos de resultados. Buscar: Debe existir un elemento que le permita al usuario buscar un registro usuario escribiendo el nombre del grupo regional , el canal debe validar la información y actualizar la pantalla según el resultado. Ordenar: Debe tener un elemento que permite ordenar la información dando clic de manera intuitiva en los títulos de las columnas de mayor a menor y de menor a mayor. Paginación: Se debe mostrar 50 resultados por página. Si la aprobación o rechazo de la gestión presenta error al confirmar mostrará mensaje de error en pantalla indicando el motivo del error. | G48: Validación de filtros - Autorización de gestiones de forma exitosa - Rechazo de gestiones de forma exitosa. - | H48: Todos
A49: CP48 | B49: Usuarios Back Office escala 7/24 | C49: Visualización del menú vertical izquierdo (Sidebar) | D49: Acceso al Módulo de administración / Logs de Auditoría | E49: Módulo visible para todos los usuarios, quienes podrán consultar y visualizar Logs del Registro completo de cualquier novedad realizada desde el control Center y en el Front de los usuarios durante 12 meses, El sistema debe generar y registrar de forma completa y precisa toda la información relacionados con la creación o cualquier novedad realizada desde el control Center, incluyendo toda la información detallada de los datos de entrada y salida, y cualquier error o excepción que se produzca durante el proceso. | G49: Mostrar información de toda la trazabilidad ejecutada por los usuarios BO en control center | H49: Todos
A50: CP49 | B50: Usuarios Back Office escala 7/24 | C50: Visualización del menú vertical izquierdo (Sidebar) | D50: Acceso al Módulo de administración / Logs de Auditoría | E50: El usuario podrá filtrar la información por los siguientes filtros de búsqueda: Tipo de novedad: Permite seleccionar el tipo de novedad dentro de las opciones del desplegable. Nombre usuario: Permite ingresar el nombre del usuario.( debe coincidir con el creado) Fecha de novedad desde - hasta: Permite ingresar la fecha desde y hasta. Tipo de identificación: Permite seleccionar el tipo de ID. Número de identificación: Permite ingresar el número de ID. Aplicativo: Permite seleccionar una de las opciones, Front - Middle Rol Usuario:Permite seleccionar el rol del usuario Número Id Empresa: Permite ingresar el número de ID de la empresa afectada. País: Seleccionable, permite seleccionar el país del usuario. | G50: Mostrar información de acuerdo a los filtros utilizados | H50: Todos
A51: CP50 | B51: Usuarios Back Office escala 7/24 | C51: Visualización del menú vertical izquierdo (Sidebar) | D51: Acceso al Módulo de administración / Logs de Auditoría | E51: Detalle por registro Resultado consulta: Nombre usuario: Se debe mostrar el nombre del usuario que realizó la novedad. Tipo ID: Se debe mostrar el tipo de ID del usuario que realizó la novedad. Número ID: Se debe mostrar el tipo de ID del usuario que realizó la novedad. Novedad: Se debe presentar el nombre de la acción realizada. Fecha - Hora: El canal debe mostrar la fecha y hora en la que se realizó la novedad. IP: Se debe presentar la IP desde la cual se realizó la novedad. Quick Action ( Ver detalle): Al dar clic debe actualizar la pantalla y mostrar mayor detalle del registro. Detalle: Una vez el usuario de clic a la opción “ver detalle” se debe actualizar la pantalla y el canal deberá mostrar la información completa de todos los registros desde la “data anterior” hasta la data posterior | G51: Mostrar detalle de la consulta de acuerdo a los campos consultados | H51: Todos
A52: CP51 | B52: Usuarios Back Office escala 7/24 | C52: Visualización del menú vertical izquierdo (Sidebar) | D52: Acceso al Módulo de administración / Logs de Auditoría | E52: Seguridad de los logs: Los logs deben ser almacenados de forma segura y protegida contra accesos no autorizados. Retención y disponibilidad de los logs: Los logs generados deben ser retenidos durante el tiempo necesario para cumplir con las regulaciones locales y las políticas internas del banco. Además, los logs deben estar disponibles para su consulta y análisis por parte del personal autorizado en caso de necesidad, utilizando las herramientas y procedimientos adecuados. Integridad y calidad de los logs: Los logs generados deben ser precisos, completos y confiables, garantizando la integridad y calidad de la información registrada. Esto incluye la verificación de la correcta captura de datos, la validación de la consistencia de la información, y la corrección de cualquier error o inconsistencia detectada en los logs. Registro de eventos relevantes: Los logs deben registrar todos los eventos relevantes relacionados con la creación de una empresa en el canal virtual regional, o cualquier novedad realizada incluyendo la información del usuario que creó la novedad, usuario que la aprobó, horas, fechas, ip, datos de los usuarios que intervienen, país y tipo de novedad. La herramienta debe permitir realizar la descarga de la información en formato pdf. | G52: Mostrará acceso a usuarios que cuenten con los permisos y mostrará todo el registro de las gestiones realizadas | H52: Todos
A53: CP52 | B53: Usuarios Back Office escala 7/24 | C53: Visualización del menú vertical izquierdo (Sidebar) | D53: Acceso al Módulo de administración / Transacciones | E53: Módulo visible para todos los usuarios, permita a los usuarios que tienen acceso al control center regional tener acceso a consultar reportes de operaciones monetarias de los últimos 12 meses realizados por usuarios en el front del canal para poder monitorear y analizar las transacciones de los clientes. Visualización de Resultados: Fecha: El canal debe mostrar la fecha en la que se procesó la transferencia. por default se presentará de la más reciente a la más antigua. País Origen: Se debe mostrar el nombre y la bandera del país origen de la operación. Tipo de Transferencia: Se debe mostrar el tipo de operación según corresponda ( Cuentas propias / cuentas de terceros) Número de Transacción: Se debe mostrar el número único de identificación de la operación a nivel del canal. Estado: Estado actual de la operación (Exitosa, pendiente de aprobación, rechazada, anulada) Monto: Se debe mostrar el valor y el tipo de la moneda por el cual se generó la transacción. Botón Ordenar: Debe existir un elemento que permita al usuario ordenar la información que se muestra en pantalla, una vez de clic al título del resultado debe ordenar la información de mayor a menor y al volver al dar clic ordena de menor a mayor. Esta funcionalidad aplica sobre: - Fecha - Monto Botón Buscar: Al dar clic se debe habilitar una barra de búsqueda que permite al usuario ingresar el “Número de transacción”, el canal debe actualizar los resultados de búsqueda teniendo en cuenta el texto ingresado, se debe habilitar un botón de “cancelar” en caso que el usuario quiera eliminar esta búsqueda. En caso que el usuario ingrese un texto que no encuentre coincidencia el canal debe mostrar “La búsqueda de (texto ingresado) no presenta resultados.” | G53: Visualización de datos de transaccionalidad de clientes que operan en la plataforma regional | H53: Todos
... A60: CP59 | B60: Usuarios Back Office escala 7/24 | C60: Gestiones Usuario BO Preparador | D60: Permisos de Bitácora de operaciones del cliente | E60: Permitir al usuario BO poder consultar las operaciones realizadas por el cliente, validando el detalle de la transacción y el estado | G60: Mostrar resultado de la bitácora realizada por el cliente | H60: Todos
A61: CP60 | B61: Usuarios Back Office escala 7/24 | C61: Gestiones Usuario BO Preparador | D61: Validar perfil de usuario BO de Preparador | E61: Este perfil únicamente permite realizar novedades de empresas y grupos del país al cual pertenece. Todas las gestiones quedarán pendientes de autorización. | G61: Muestra Información de Lectura en Escala 7x24 | H61: Todos | Z61: -.
A62: CP61 | B62: Usuarios Back Office escala 7/24 | C62: Gestiones Usuario BO Preparador | D62: Usuario operador debe existir en la banca local | E62: Permitir al usuario BO adicionar al operador del mismo país dominio al cliente en CC PER | G62: Adición de usuario exitoso | H62: Todos
A63: CP62 | B63: Usuarios Back Office escala 7/24 | C63: Gestiones Usuario BO Preparador | D63: Usuario operador debe existir en la banca local | E63: Uusuario BO adicione operador de país dominio diferente al cliente en CC PER | G63: No permitir adicionar usuario | H63: Todos
A64: CP63 | B64: Usuarios Back Office escala 7/24 | C64: Gestiones Usuario BO Preparador | D64: Usuario operador debe existir en la banca local | E64: Permitir al usuario BO preparador todas las configuraciones siguientes a usuarios que pertenencen al mismo país dominio: Configuración de usuarios Mantenimiento de usuarios Asociar usuario a Empresas Eliminar usuario de empresas Inactivar usuario de empresas Modificar usuario de empresas | G64: Configuraciones de usuarios exitosas | H64: Todos
A65: CP64 | B65: Usuarios Back Office escala 7/24 | C65: Gestiones Usuario BO Preparador | D65: Visualizar productos activos del cliente en CC | E65: Usuario BO Preparador del mismo país dominio configure Productos permisos desde CC | G65: Configuración de conjuntos permisos exitoso | H65: Todos
A66: CP65 | B66: Usuarios Back Office escala 7/24 | C66: Gestiones Usuario BO Preparador | D66: Visualizar productos con estado diferente a activo del cliente en CC | E66: Usuario BO Operador no le permita configurar conjuntos permisos de productos con estado diferente a activo | G66: Configuración de conjuntos permisos fallida | H66: Todos
A67: CP66 | B67: Usuarios Back Office escala 7/24 | C67: Gestiones Usuario BO Preparador | D67: Cliente deberá estar marcado como multilatino y tener productos activos | E67: Permitir al usuario BO preparador realizar todas las configuraciones siguientes clientes que pertenencen al mismo país dominio: Consulta esquema de firmas Creación de esquema de firmas Modificación esquema de firmas Eliminación de esquema de firmas | G67: Configuraciones de esquema de firmas exitosas | H67: Todos
A68: CP67 | B68: Usuarios Back Office escala 7/24 | C68: Gestiones Usuario BO Preparador | D68: Cliente deberá estar marcado como multilatino y tener productos | E68: Permitir al usuario BO preparador realizar todas las configuraciones siguientes a clientes que pertenencen al mismo país dominio: Deshabilitar cuenta Eliminar cuenta Habilitar cuenta | G68: Configuraciones de cuenta exitosas | H68: Todos
A69: CP68 | B69: Usuarios Back Office escala 7/24 | C69: Gestiones Usuario BO Preparador | D69: Usuario operador debe existir en la banca local | E69: Permitir al usuario BO preparador realizar todas las configuraciones siguientes a usuarios que pertenencen al mismo país dominio: Creación de roles Modificación de roles Eliminación de roles | G69: Configuraciones de roles exitosas | H69: Todos
A70: CP69 | B70: Usuarios Back Office escala 7/24 | C70: Gestiones Usuario BO Preparador | D70: Usuario operador debe existir en la banca local | E70: Permitir asignar a los usuarios del mismo país dominio la funcionalidad de Buzón de notificaciones | G70: Asignación de buzón de notificaciones exitosa | H70: Todos
A71: CP70 | B71: Usuarios Back Office escala 7/24 | C71: Gestiones Usuario BO Autorizador | E71: Realizar consultas de clientes, usuarios, productos, esquemas de firmas, roles de todos los países | G71: Consultas exitosas | H71: Todos
A72: CP71 | B72: Gestión cliente CC banca local | C72: Escala 7x24 no permite crear empresas Multilatinas sin existencia Local | D72: En la pantalla de Alta de Cliente de CC local debe existir la segregarción para crear clientes normales o exclusivos de los países y una opción donde se perfile un cliente Multilatino | E72: Debe existir una opción donde el administrador realiza la segregación de clientes y permitirle marcar a un cliente en CC local como multilatino | G72: Marcacción de cliente multilatino exitosa | H72: Todos
A73: CP72 | B73: Gestión cliente CC Escala 7/24 | C73: Crear solicitud de cambio con Dominio de cada uno de los paises PA,SV,HN,CR Con usuario Operador | D73: Cliente debe estar marcado como multilatino en CC de cada banca local | E73: No debe permitir asignar cabecera holding a un mismo cliente que ya se encuentra marcado como cabecera. | G73: No asignar a mismo cliente como cabecera holding | H73: Todos
A74: CP73 | B74: Gestión cliente CC Escala 7/24 | C74: Crear solicitud de cambio con Dominio de cada uno de los paises PA,SV,HN,CR Con usuario Operador | D74: Cliente debe estar marcado como multilatino en CC de cada banca local | E74: Seleccionar la opción de administración Seleccionar empresas Puede Utilizar los filtros: País Tipo de Documento Número de Documento Nombre Empresa Estado: mostrar en lista los siguientes estado: Activo Activo Pen.Inactivación Activo Pen.Eliminación Alta Pend. Autorización Modi.Pend. Autorización Inactivo Pend. Habilitación Inactivo Seleccionar Buscar debe mostrar el resultado Seleccionar Detalle de la sociedad a modificar Al ingresar al detalle debe visualizar los botones Volver-Modificar-Eliminar-Deshabilitar Sino utiliza ningun filtro y selecciona el botón de consultar deberá devolver el resultado de todos los registros sin hacer distinción del país dominio del usuario BO Mostrar botón de crear 'cliente' | G74: Visualización de registros de clientes y gestión pendiente de autorización | H74: Todos
A75: CP74 | B75: Gestión cliente CC Escala 7/24 | C75: Crear solicitud de cambio con Dominio de cada uno de los paises PA,SV,HN,CR Con usuario autorizante | D75: Cliente debe estar marcado como multilatino en CC local | E75: Seleccionar la opción de administración Seleccionar empresas Puede Utilizar los filtros: País Tipo de Documento Número de Documento Nombre Empresa Estado: mostrar en lista los siguientes estado: Activo Activo Pen.Inactivación Activo Pen.Eliminación Alta Pend. Autorización Modi.Pend. Autorización Inactivo Pend. Habilitación Inactivo Seleccionar Buscar debe mostrar el resultado Seleccionar Detalle de la sociedad a modificar Al ingresar al detalle debe visualizar los botones Volver-Modificar-Eliminar-Deshabilitar Sino utiliza ningun filtro y selecciona el botón de consultar deberá devolver el resultado de todos los registros sin hacer distinción del país dominio del usuario BO Mostrar botón de crear 'cliente' | G75: Visualización de registros de clientes, la gestión podrá autorizarla un usuario autorizante de su mismo dominio y por un super usuario de cualquier dominio. | H75: Todos
A76: CP75 | B76: Gestión cliente CC Escala 7/24 | C76: Crear solicitud de cambio con Dominio de cada uno de los paises PA,SV,HN,CR Con Super usuario | D76: Cliente debe estar marcado como multilatino en CC local | E76: Seleccionar la opción de administración Seleccionar empresas Puede Utilizar los filtros: País Tipo de Documento Número de Documento Nombre Empresa Estado: mostrar en lista los siguientes estado: Activo Activo Pen.Inactivación Activo Pen.Eliminación Alta Pend. Autorización Modi.Pend. Autorización Inactivo Pend. Habilitación Inactivo Seleccionar Buscar debe mostrar el resultado Seleccionar Detalle de la sociedad a modificar Al ingresar al detalle debe visualizar los botones Volver-Modificar-Eliminar-Deshabilitar Sino utiliza ningun filtro y selecciona el botón de consultar deberá devolver el resultado de todos los registros sin hacer distinción del país dominio del usuario BO Mostrar botón de crear 'cliente' | G76: Visualización de registros de clientes, la gestión podrá autorizarla un super usuario de cualquier dominio. | H76: Todos
A77: CP76 | B77: Gestión cliente CC Escala 7/24 | C77: Validación de Alta de clientes nuevos sin marcación | D77: Cliente no debe estar marcado como multilatino en CC local | E77: Alta al cliente desde CC de escala 7/24 con usuario operador, autorizador y super usuario | G77: No devolverá información de un cliente que no se encuentre marcado como multilatino en CC local. | H77: Todos
A78: CP77 | B78: Gestión cliente CC Escala 7/24 | C78: Validaciones de máscaras en formatos de tipo documento y número de documento de clientes | D78: Realizar las validaciones de los formatos en el número de documento, este formato debe estár acorde con la selección de información que se realizó en los campos de País y Tipo de documento | E78: El formato presentado en el campo de número de documento debe ser el exigido en cada uno de los tipos de documento, por ejemplo si se selecciona CR como país, ID persona física, el formado debe ser de 10 caracteres. | F78: Greivin: Para efectos del proyecto se esta elaborando un documento que contiene toda esta información | G78: Pedir a los países que compartan los criterios de sus documentos. Por Ej para SV el NIT/NITE son 14 caracteres numéricos | H78: Todos
A79: CP78 | B79: Gestión cliente CC Escala 7/24 | C79: Funcionalidad de botón regresar | D79: Validar la funcionalidad del boton regresar, al oprimirlo debe mostrar al usuario la pantalla anterior, | E79: Debe mostrar en forma existosa la pantalla anterior | G79: Devolver al paso anterior | H79: Todos
A80: CP79 | B80: Gestión cliente CC Escala 7/24 | C80: Verificación de mensajes de error en alta cliente | D80: Validar los mensajes de error, ejecuntando las siguientes acciones: - No colocar datos y oprimir la acción de buscar clientes. - Se debe colocar un número de ID que no existe en el país. - Tratar de colocar caracteres que no corresponden al formato del ID como por ejemplo caracteres alfanumericos cuando se selecciona el ID de persona física en CR. | E80: Los mensajes de errores o mensajes de precaución deben ser acorde al error que se esta generando y se deben almacenar en el enumerado el cual es parametrizable | F80: Greivin: Se debe validar con LD si hay un mensaje específico para cada error. | G80: Brindar el mensaje esperado por cada error (escenario) | H80: Todos
A81: CP80 | B81: Gestión cliente CC Escala 7/24 | C81: Verificación de mensajes de error en alta cliente | D81: Validar el mensaje de error una vez que se ingresan todos los datos en forma correcta, se elimina la selección de "Cliente MultiLatino" y se realiza la acción de buscar. | E81: Se debe desplegar un mensaje de error, este mensaje debe estar acorde al error que se esta generando. | F81: Greivin: Los mensajes en estos momentos se están cargando en los enumerados. El caso de prueba lo que trata de probar es ingresar todos los datos en forma correcta pero eliminar una selección que viene desde páginas anteriores | G81: Brindar el mensaje esperado por cada error. ¿El mensaje no debería deplegarse automáticamente al desmarcar Cliente Multilatino? | H81: Todos
A82: CP81 | B82: Gestión cliente CC Escala 7/24 | C82: Alta de cliente Multilatino | D82: Realizar la inclusión de los datos en los campos de Cliente Multilatino, País, Tipo de Documento y Número de Documento con los datos correctos y realizar la acción de Buscar, esta acción se debe realizar con las datos utilizando un cliente de Panama | E82: Se debe presentar los datos respectivos y continuar con el flujo normal | F82: Greivin: Se crean casos de pruebas por cada uno de los países. | G82: Se debe realizar al menos un caso por cada tipo de documento de cada país | H82: Todos
A83: CP82 | B83: Gestión cliente CC Escala 7/24 | C83: Alta de cliente Multilatino | D83: Realizar la inclusión de los datos en los campos de Cliente Multilatino, País, Tipo de Documento y Número de Documento con los datos correctos y realizar la acción de Buscar, esta acción se debe realizar con las datos utilizando un cliente de Costa Rica | E83: Se debe presentar los datos respectivos y continuar con el flujo normal | G83: Se debe realizar al menos un caso por cada tipo de documento de cada país | H83: Todos
A84: CP83 | B84: Gestión cliente CC Escala 7/24 | C84: Alta de cliente Multilatino | D84: Realizar la inclusión de los datos en los campos de Cliente Multilatino, País, Tipo de Documento y Número de Documento con los datos correctos y realizar la acción de Buscar, esta acción se debe realizar con las datos utilizando un cliente de El Salvador | E84: Se debe presentar los datos respectivos y continuar con el flujo normal | G84: Se debe realizar al menos un caso por cada tipo de documento de cada país | H84: Todos
A85: CP84 | B85: Gestión cliente CC Escala 7/24 | C85: Alta de cliente Multilatino | D85: Realizar la inclusión de los datos en los campos de Cliente Multilatino, País, Tipo de Documento y Número de Documento con los datos correctos y realizar la acción de Buscar, esta acción se debe realizar con las datos utilizando un cliente de Honduras | E85: Se debe presentar los datos respectivos y continuar con el flujo normal | G85: Se debe realizar al menos un caso por cada tipo de documento de cada país | H85: Todos
A86: CP85 | B86: Gestión cliente CC Escala 7/24 | C86: Alta de cliente Multilatino | D86: Realizar nuevamente el proceso de creación de clientes, utilizando un dato de un cliente previamente creado. | E86: Se debe desplegar un mensaje de error, este mensaje debe estar acorde al error que se esta generando. por ejemplo: Cliente existente | F86: Greivin: igual con los demás mensajes, una vez que se carguen los enumerados en BEL podríamos tener la relación de estos | G86: Brindar el mensaje esperado por cada error | H86: Todos
A87: CP86 | B87: Gestión cliente CC Escala 7/24 | C87: Alta de cliente Multilatino | D87: Después de ejecutar la acción de busqueda, se deben desplegar todos los campos de la pantalla de Datos filiatorios | E87: Deben aparecer todos los datos que se encuentran en el diseño funcional personalizado en el requerimiento | G87: Visualización de todos los campos filiatorios | H87: Todos
A88: CP87 | B88: Gestión cliente CC Escala 7/24 | C88: Modulo "Administración" | D88: Visualización del módulo administración | E88: En el módulo “Administración” estará el botón de “Crear Grupo” este botón estará habilitado para todos los usuarios al dar click se actualiza la pantalla y debe mostrar el track de los 6 pasos para la creación con barra de avance: 1 Datos 2 Empresa 3 Membresía 4 Administración 5 Transacciones Permitidas 6 Resumen | G88: Acceso al modulo de administración con usuarios Bo Preparadores, autorizadores y super usuarios | H88: Todos
A89: CP88 | B89: Gestión alta cliente CC Escala 7/24 | C89: Autorización de clientes y grupos regionales Usuario Autorizador | D89: Visualización y acceso al menú autorizaciones de CC escala 7/24 | E89: - Autorización de alta de cliente y grupo regional no podrán realizarse de forma parcial. - Visualización de gestiones pendientes del mismo país dominio del cliente y usuario BO preparador. - Autorización unicamente desde el menú operador | G89: Autorización de gestiones clientes y grupos regionales exitosas | H89: Todos
A90: CP89 | B90: Gestión alta cliente CC Escala 7/24 | C90: Autorización de clientes y grupos regionales Super Usuario | D90: Visualización y acceso al menú autorizaciones de CC escala 7/24 | E90: - Autorización de alta de cliente y grupo regional no podrán realizarse de forma parcial. - Visualización de todas las gestiones pendientes, sin distinción del país dominio del usuario preparador y/o cliente - Autorización unicamente desde el menú operador | G90: Autorización de gestiones clientes y grupos regionales exitosas | H90: Todos
A91: CP90 | B91: Gestión alta cliente CC Escala 7/24 | C91: Paso 1 "Datos" Creación de grupos regionales Usuario BO preparador | D91: Validación del campo nombre grupo regional | E91: Campo alfanumérico y obligatorio, permitir ingresar el nombre del grupo regional | G91: Asignación del nombre del grupo regional | H91: Todos
A92: CP91 | B92: Gestión alta cliente CC Escala 7/24 | C92: Paso 1 "Datos" Creación de grupos regionales Usuario BO preparador | D92: Validación del Tipo de Administración | E92: Se mostrará en lista las 2 opciones de administración ´Dual´y 'Simple', campo obligatorio | G92: Selección de un tipo de administración | H92: Todos
A93: CP92 | B93: Gestión alta cliente CC Escala 7/24 | C93: Paso 1 "Datos" Creación de grupos regionales Usuario BO preparador | D93: Validación de casa matriz con todos los dominios, HN, CR, SV, PA | E93: El País donde se crea el Grupo Regional será denominado: “Casa Matriz" y mostrará el país de dominio del usuario que ejecute la gestión, por ejemplo si el usuario BO es origen HN mostrará en el campo casa matriz 'Honduras' - Campo obligatorio | G93: Selección de país de casa matriz de acuerdo al dominio del usuario BO | H93: Todos
A94: CP93 | B94: Gestión alta cliente CC Escala 7/24 | C94: Paso 1 "Datos" Creación de grupos regionales Usuario BO preparador | D94: Validación del campo Presencia regional | E94: - Mostrar en lista los nombres de los países, HN, CR, PA, SV y previamente marcado el país del dominio del usuario BO y casa matriz | G94: Marcación exitosa de los países seleccionados | H94: Todos
A95: CP94 | B95: Gestión alta cliente CC Escala 7/24 | C95: Paso 1 "Datos" Creación de grupos regionales Usuario BO preparador | D95: Validación del campo Presencia regional | E95: - Mostrar dentro de la lista de países la opción "Todos los países", la cual permitirá seleccionar todos los países | G95: Marcación exitosa de la opción "Todos los países". | H95: Todos
A96: CP95 | B96: Gestión alta cliente CC Escala 7/24 | C96: Paso 1 "Datos" Creación de grupos regionales Usuario BO preparador | D96: Validación de destinos autorizados, el campo se mostrará apagado por default | E96: - Campo no obligatorio - Activar el swicth de 'Valida destinos autorizados' las empresas asociadas a la casa matriz podrán visualizar y acceder a los destinos autorizados de todo el grupo regional. - Desactivar el swicth de 'Valida destino autorizados' las empresas asociadas al grupo regional no podrán visualizar los destinos autorizados de las sociedades relacionadas. | G96: Activar y desactivar el swicth de 'Validar destinos autorizados' | H96: Todos
A97: CP96 | B97: Gestión alta cliente CC Escala 7/24 | C97: Paso 1 "Datos" Creación de grupos regionales Usuario BO preparador | D97: Mostrar botones de regresar y continuar | E97: Selecicón de botones 'Regresar' y 'Continuar' | F97: Greivin: igual con los demás mensajes, una vez que se carguen los enumerados en BEL podríamos tener la relación de estos | G97: Validación de botones 'Regresar' y 'Continuar' | H97: Todos
A98: CP97 | B98: Gestión alta cliente CC Escala 7/24 | C98: Paso 2 "Empresas" Búsqueda y selección de empresas a adicionar al grupo regional, usuario BO preparador | D98: Selección campo País Origen de acuerdo al domino del usuario BO preparador | E98: - Mostrar en el campo 'País Origen' unicamente el país del usuario preparador BO y casa matriz del cliente a crear, por ejemplo, si el usuario BO es domino SV y la casa matriz tambien es SV, en el campo 'País Origen' deberá mostrar El Salvador - Campo obligatorio | G98: Selección del país de casa matriz de acuerdo al dominio del usuario BO | H98: Todos
A99: CP98 | B99: Gestión alta cliente CC Escala 7/24 | C99: Paso 2 "Empresas" Búsqueda y selección de empresas a adicionar al grupo regional, usuario BO preparador | D99: Selección de tipo de identiificación del cliente | E99: Mostrará los tipos de identificación de acuerdo al dominio del usuario BO y la casa matriz, segun se detalla a continuación: El Salvador: NIT y NITE: 17 caracteres numéricos separados por guiones Máscara: ####-######-###-# Costa Rica Cédula jurídica: 10 caracteres numéricos separados por guiones Máscara: #-###-###### Honduras: RTN: 14 caracteres numéricos sin guiones Máscara: ############## Panamá: RUC: 20 caracteres numéricos separados por guiones Máscara: #########-##-######### Otro RUC: 15 carcateres sin guiones Máscara: ############### Campo obligatorio | G99: Mostrar tipos de documentos y máscaras segun el país dominio del usuario BO y casa matriz | H99: Todos
A100: CP99 | B100: Gestión alta cliente CC Escala 7/24 | C100: Paso 2 "Empresas" Búsqueda y selección de empresas a adicionar al grupo regional, usuario BO preparador | D100: Validación de número de documento | E100: Ingresar número de documento correcto, de acuerdo al país dominio del usuario BO y casa matriz Campo obligatorio | G100: Validación exitosa del número de documento | H100: Todos
A101: CP100 | B101: Gestión alta cliente CC Escala 7/24 | C101: Paso 2 "Empresas" Búsqueda y selección de empresas a adicionar al grupo regional, usuario BO preparador | D101: Validación de número de documento | E101: Ingresar número de documento incorrecto, se realiza validación con el core y deberá mostrar mensaje en pantalla indicando el error de número de documento incorrecto. Campo obligatorio | G101: No permite conitnuar con el proceso | H101: Todos
A102: CP101 | B102: Gestión alta cliente CC Escala 7/24 | C102: Paso 2 "Empresas" Búsqueda y selección de empresas a adicionar al grupo regional, usuario BO preparador | D102: Validación de número de documento | E102: Seleccionar tipo de documento diferente al número de documento del cliente, deberá mostrar mensaje de error indicando que el cliente no existe en el core del país dominio del usuario BO y país casa matriz Campo obligatorio | G102: Mostrar error en pantalla indicando que el cliente no existe | H102: Todos
A103: CP102 | B103: Gestión alta cliente CC Escala 7/24 | C103: Paso 2 "Empresas" Búsqueda y selección de empresas a adicionar al grupo regional, usuario BO preparador | D103: Verificación de botones regresar y consultar | E103: - Seleccionar botón regresar, devolverá al paso anterior "Datos" - Selección de botón consultar, debe permitir continuar al siguiente paso. | G103: Validación exitosa de los botones | H103: Todos
A104: CP103 | B104: Gestión alta cliente CC Escala 7/24 | C104: Paso 2 "Empresas" Búsqueda y selección de empresas a adicionar al grupo regional, usuario BO preparador | D104: Empresa NO debe estar marcada como multilatina en CC de BEL local | E104: Mostrará error indicando que la empresa no existe. | G104: Mostrará mensaje de error de acuerdo al catálogo de errores. | H104: Todos
A105: CP104 | B105: Gestión alta cliente CC Escala 7/24 | C105: Paso 2 "Empresas" Búsqueda y selección de empresas a adicionar al grupo regional, usuario BO preparador | D105: Empresa deberá estar marcada como multilatina en CC de BEL local | E105: Mostrará resultado de la búsqueda de la empresa y mostrará los siguientes campos bloqueados y poblados: - País Origen: Mosrará bandera y nombre del país - Tipo de identificación: Mostrará el nombre del tipo de la identificación - Número identificación: mostrará el número de identificación respetando la máscara - Razon social: Mostrará el nombre de la razon social de la sociedad - Segmento: mostrará el tipo de segmento ejemplo: Empresarial, corporativo, PYME, multilatino. - Mostrará botón 'Seleccionar empresa' | G105: Mostrar información del cliente de acuerdo a lo registrado en cada core y banca en línea. | H105: Todos
A106: CP105 | B106: Gestión alta cliente CC Escala 7/24 | C106: Paso 2 "Empresas" Búsqueda y selección de empresas a adicionar al grupo regional, usuario BO preparador | D106: Empresa deberá estar marcada como multilatina en CC de BEL local | E106: - Al seleccionar el botón 'Seleccionar empresa' deberá mostrar todas las empresas asociadas a la casa matriz y de los países previamente seleccionados. - Mostrará mensaje indicando los isguiente: 'Empresa fue seleccionda exitosamente, si desea agregar más empresas diligencie nuevamente los campos de país origen, tipo de identificación, y número de identificación.' | G106: Visualización de clientes previamente seleccionados de acuerdo al campo 'Presencia Regional'. | H106: Todos
...

Sheet HU009_PER - Grupo de Productos
A1: Nomenclatura | B1: Requerimiento | C1: Título | D1: Precondición | E1: Descripción | F1: Alcance | G1: Condición | H1: Resultado | I1: País Responsable
A2: CP01 | B2: Grupo de Productos / Escala 7x24 Gestión desde Control Center | C2: Criterio 1 Características Grupo de Productos | D2: Usuario BO debe existir en Control Center Escala 7x24 | E2: Se debe habilitar una opción que permita a los usuarios administradores dentro del nuevo módulo regional crear, editar, consultar o eliminar grupo de productos que facilitarán la asignación de productos a los usuarios y a los esquemas de firmas definidos. | F2: Visualización a la funcionalidad de grupo de productos. | H2: Acceso a la funcionalidad de grupo de productos. | I2: Todos | L2: Consolidado de casos | M2: =COUNTA(I2:I212) -> 211
A3: CP02 | B3: Grupo de Productos / Escala 7x24 Gestión desde Control Center | C3: Criterio 1 Características Grupo de Productos | D3: Usuario BO debe existir en Control Center Escala 7x24 | E3: Los productos a los que el usuario BO puede acceder para autogestionar las novedades de grupos de productos corresponde únicamente de productos asignados a la empresa desde el control center. | F3: Gestionar grupo de productos | G3: - Cliente deberá tener productos activos | H3: Gestionar grupo de productos | I3: Todos
A4: CP03 | B4: Grupo de Productos / Escala 7x24 Gestión desde Control Center | C4: Criterio 1 Características Grupo de Productos | D4: Usuario BO debe existir en Control Center Escala 7x24 | E4: Todos los textos cómo modales deben ser incluidos por una herramienta de gestión de contenidos o CMS paramétricos en caso que cuando tengamos los siguientes incrementales se puedan editar de manera sencilla. | F4: Poseer una herramienta de gestión de contenidos | H4: Brindar mantenimiento cuando sea requerido | I4: Todos
A5: CP04 | B5: Grupo de Productos / Escala 7x24 Gestión desde Control Center | C5: Criterio 1 Características Grupo de Productos | D5: Usuario BO debe existir en Control Center Escala 7x24 | E5: Una vez el usuario acceda a esta funcionalidad mientras carga la información que se mostrará en pantalla, se debe mostrar el “Skeleton” de la funcionalidad. | F5: Visualizar la estructura de la funcionalidad con grupos de productos, roles y esquema de firmas | H5: Mostrar los campos que contiene la funcionalidad en formato lectura | I5: Todos
A6: CP05 | B6: Grupo de Productos / Escala 7x24 Gestión desde Control Center | C6: Criterio 1 Características Grupo de Productos | D6: Usuario BO debe existir en Control Center Escala 7x24 | E6: Si el usuario visualiza el contenido en inglés los textos del canal deben corresponder. | F6: Permitir al usuario gestionar grupo de productos en idioma inglés | H6: Mostrar traducidos los campos al inglés y oermitir ejecutar la gestión. | I6: Todos
A7: CP06 | B7: Grupo de Productos / Escala 7x24 Gestión desde Control Center | C7: Criterio 2 - Creación Grupo de Productos | D7: Usuario BO debe existir en Control Center Escala 7x24 | E7: 2.3 Creación Grupo: Título: Nombre del grupo de productos Elemento para regresar | F7: Describir el nombre de la funcionalidad | G7: Mostrar campos en formato lectura | H7: Mostrar campos en formato lectura | I7: Todos
A8: CP07 | B8: Grupo de Productos / Escala 7x24 Gestión desde Control Center | C8: Criterio 2 - Creación Grupo de Productos | D8: Usuario BO debe existir en Control Center Escala 7x24 | E8: Descripción: Asigne un nombre al nuevo grupo de productos Espacio para el nombre: Se habilita la opción para que el usuario ingrese el nombre del grupo de productos que creará. Características del campo: - Alfanumérico. - Longitud máxima de 50 caracteres, debe habilitar un contador de caracteres que muestre al usuario la longitud máxima, los caracteres usados y los caracteres disponibles. - Longitud mínima de 5 caracteres, si no cumple con esta característica no permite continuar la creación, debe tener un elemento informe “ la longitud mínima es de 5 caracteres”. - Debe validar que el nombre ingresado sea único para el grupo regional, es decir no podrá tener el nombre repetido, en caso que intente crear un grupo con el mismo nombre el canal debe mostrar mensaje: “Este nombre ya se usó en otro grupo regional. Asigne uno nuevo” | F8: Permitir al usuario asignar un nombre personalizado al grupo de productos | H8: Asignar nombre personalizado al grupo de producto | I8: Todos
A9: CP08 | B9: Grupo de Productos / Escala 7x24 Gestión desde Control Center | C9: Criterio 2 - Creación Grupo de Productos | D9: Usuario BO debe existir en Control Center Escala 7x24 | E9: Botón de “Asignar” permita continuar con el proceso de creación del Grupo de productos. | F9: Accesibilidad al botón de agregar | G9: - Mostrará botón de asignar cuando se haya colocado un nombre al grupo de producto | H9: Visualización y acceso al botón de 'Asignar' | I9: Todos
A10: CP09 | B10: Grupo de Productos / Escala 7x24 Gestión desde Control Center | C10: Criterio 3 - Búsqueda y Selección de productos | D10: Asignar nombre al grupo de productos | E10: Pantalla: 3.1 Título del Header: “Elección de productos” 3.2 Elemento regresar: Debe existir un botón o elemento que le permita al usuario regresar a la pantalla anterior en cualquier momen. | F10: El canal debe actualizar la pantalla para sugerir al usuario realizar la selección de los productos que conformarán el grupo de productos que está creando. | G10: Se debe presentar todos los productos que tienen las empresas que conforman el grupo regional de acuerdo a lo parametrizado en el control center regional. | H10: Visualizar título de la pantalla y botón de regresar | I10: Todos
A11: CP10 | B11: Grupo de Productos / Escala 7x24 Gestión desde Control Center | C11: Criterio 3 - Búsqueda y Selección de productos | D11: Asignar nombre al grupo de productos | E11: 3.3 Títulos por columnas del resultado de productos: País: Debe mostrar bandera e iniciales del país al que pertenece el producto Empresa: Debe mostrar el nombre de la empresa a la que pertenece el producto. Nombre del Producto: se debe mostrar el nombre o el alias si está asignado de lo contrario mostrará el nombre de la empresa. Tipo de producto: Debe mostrar el tipo de la cuenta a la que pertenece el producto ( Cuenta ahorro, cuenta corriente, cuenta ahorro maestra) Número de producto: debe mostrar el número de la cuenta enmascarado. Checkbox: debe tener por cada fila de resultado este elemento que permite realizar selección de manera individual. | F11: - Permitir al usuario seleccionar el producto para la creación del grupo de productos. - Marcar y desmarcar productos de forma correcta | G11: -Visualizar las cuentas de las sociedades con las cuales se ingresó al módulo regional. | H11: Selección de productos de forma exitosa. | I11: Todos
A12: CP11 | B12: Grupo de Productos / Escala 7x24 Gestión desde Control Center | C12: Criterio 3 - Búsqueda y Selección de productos | D12: Asignar nombre al grupo de productos | E12: 3.4 Paginación: En la pantalla se debe presentar la paginación mostrando el número de páginas totales que arroja la consulta. - La paginación se debe presentar en la parte superior del resultado. - Se presentarán hasta 50 registros por página, de acuerdo a la información obtenida del resultado de la consulta, para llegar a la parte inferior el usuario podrá usar el scroll y el teclado. | F12: - La paginación se presentará de acuerdo al resultado de la búsqueda | G12: - Si no posee 50 registros no mostrará paginación. | H12: Mostrará paginación a partir de los 50 registros | I12: Todos
A13: CP12 | B13: Grupo de Productos / Escala 7x24 Gestión desde Control Center | C13: Criterio 3 - Búsqueda y Selección de productos | D13: Asignar nombre al grupo de productos | E13: 3.5 Opción para operar con todos los productos: El canal debe contar con una opción que permite al usuario seleccionar si desea “operar con todos los productos”. Una vez seleccionado se muestra la totalidad de los productos marcados de forma automática en el checkbox. | F13: Permitir seleccionar todos los registros con un solo clic en el botón de checkbox y al seleccionarlo se marquen automáticamente todos los productos del mismo tipo o de manera individual. | H13: Marcación de todos los productos de forma exitosa. | I13: Todos
A14: CP13 | B14: Grupo de Productos / Escala 7x24 Gestión desde Control Center | C14: Criterio 3 - Búsqueda y Selección de productos | D14: Asignar nombre al grupo de productos | E14: 3.6 Búsqueda avanzada de productos Buscar: Al dar clic se debe habilitar una barra de búsqueda que permite al usuario ingresar el nombre del producto, el canal debe actualizar los resultados de búsqueda teniendo en cuenta el texto ingresado, se debe habilitar un botón de “cancelar” en caso que el usuario quiera eliminar esta búsqueda. En caso que el usuario ingrese un texto que no encuentre coincidencia el canal debe mostrar “La búsqueda de (texto ingresado) no presenta resultados. Filtrar: Adicional debe contar con un elemento que permite buscar productos con filtros específicos, al dar clic sobre el texto se sobrepone en la pantalla la información detallando los filtros que se podrán aplicar para la búsqueda de productos así: Título: Filtrar Botón “x”: Regresa a la pantalla anterior. Texto: Aplique las opciones de filtrado que desea | F14: El canal debe permitir al usuario buscar productos por las funciones de Buscar y filtrar | H14: Búsqueda y uso de filtros exitoso. | I14: Todos
A15: CP14 | B15: Grupo de Productos / Escala 7x24 Gestión desde Control Center | C15: Criterio 3 - Búsqueda y Selección de productos | D15: Asignar nombre al grupo de productos | E15: 3.6.1 País: permite seleccionar uno o todos los países, la opción que aquí se muestre dependerá de donde el grupo tenga presencia mostrando únicamente los países donde tiene productos. | F15: Selección de 1 o varios productos de los países en donde tiene presencia | H15: Visualizar los productos del país o países en donde tiene presencia el grupo empresarial | I15: Todos
A16: CP15 | B16: Grupo de Productos / Escala 7x24 Gestión desde Control Center | C16: Criterio 3 - Búsqueda y Selección de productos | D16: Asignar nombre al grupo de productos | E16: 3.6.2 Empresa: Permite seleccionar una o todas las empresas del grupo de acuerdo a la selección de empresas al iniciar la sesión. | F16: Selección de empresas ligadas al grupo regional | H16: Visualizar las empresas ligadas al grupo regional | I16: Todos
A17: CP16 | B17: Grupo de Productos / Escala 7x24 Gestión desde Control Center | C17: Criterio 3 - Búsqueda y Selección de productos | D17: Asignar nombre al grupo de productos | E17: 3.6.3 Tipo de Producto: debe mostrar los productos habilitados en el módulo regional, para el MVP debe mostrar únicamente cuentas Ahorros y Corriente. y en caso que el Grupo regional tenga presencia en Costa Rica y tenga cuenta con naturaleza “ahorro maestra” debe mostrar esta opción. | F17: Mostrar los productos activos que posea el cliente | G17: Para el caso de CR deberá mostrar cuentas de Ahorro Maestras. | H17: Selección de los productos activos que posea el cliente exitosamente. | I17: Todos
A18: CP17 | B18: Grupo de Productos / Escala 7x24 Gestión desde Control Center | C18: Criterio 3 - Búsqueda y Selección de productos | D18: Asignar nombre al grupo de productos | E18: 3.6.4 Número de cuenta: Permite al usuario seleccionar el número de la cuenta desde el cual se puede realizar la transferencia. | F18: Selección del número de cuenta desde donde se hará la transferencia | G18: Número de producto deberá mostrarse enmascarado | H18: Selección del número de cuenta desde donde se hará la transferencia | I18: Todos
A19: CP18 | B19: Grupo de Productos / Escala 7x24 Gestión desde Control Center | C19: Criterio 3 - Búsqueda y Selección de productos | D19: Asignar nombre al grupo de productos | E19: Una vez presentados los filtros el canal debe mostrar las opciones: 3.6.5 Botón “Borrar": al dar clic debe eliminar los filtros de búsqueda ingresados por el usuario. 3.6.6 Botón “Aplicar”: Al dar clic el canal actualiza la pantalla donde muestra los productos, mostrando como resultado únicamente productos que cumplan con los criterios buscados, en caso que el usuario requiera seleccionar o eliminar alguna selección la podrá aplicar la novedad de manera manual. En la parte superior del resultado se debe mostrar el nombre del filtro aplicado y una opción en el mismo texto que permita “eliminar” el filtro. Adicional se debe habilitar el elemento de “borrar filtros” al dar clic elimina todos los filtros aplicados. En caso que el usuario al buscar productos para conformar un "Grupo de Productos" y utilice la funcionalidad de “filtro o búsqueda” no se debe eliminar la selección realizada previamente. En caso que el usuario aplique filtros y no encuentra coincidencia debe mostrar “La búsqueda no presenta resultados” | F19: Al aplicar el filtro deberá mostrar el resultado de acuerdo a los filtros utilizados. | H19: Al aplicar el filtro deberá mostrar el resultado de acuerdo a los filtros utilizados. | I19: Todos
A20: CP19 | B20: Grupo de Productos / Escala 7x24 Gestión desde Control Center | C20: Criterio 3 - Búsqueda y Selección de productos | D20: Asignar nombre al grupo de productos | E20: 3.7 Ordenar: Debe existir una opción en el título que permita ordenar los resultados teniendo en cuenta el título así “De la A a la Z” o “De la Z a la A”, aplica para la columna de “Empresa” | F20: Permitir ordenar los resultados de acuerdo a un rango | H20: Ejecutar orden de resultados mediante un rango. | I20: Todos
A21: CP20 | B21: Grupo de Productos / Escala 7x24 Gestión desde Control Center | C21: Criterio 3 - Búsqueda y Selección de productos | D21: Asignar nombre al grupo de productos | E21: 3.8 Selección de productos: Se debe presentar en pantalla todos los productos a los que tiene acceso el usuario administrador, para continuar con la creación del grupo de productos debe estar seleccionado al menos un producto. El usuario podrá seleccionar uno, varios o todos los productos para conformar un grupo de productos. Teniendo en cuenta que al lado del producto debe incluir un checkbox que al dar clic permite seleccionar el producto hará parte del Grupo, adicional debe mostrar de manera visual el número total de los productos seleccionados. | F21: Seleccionar los productos que pertenecerán al grupo de productos por medio de un checkbox | G21: - Selección de al menos 1 producto para continuar con el flujo | H21: Seleccionar los productos para la creación del grupo productos. | I21: Todos
A22: CP21 | B22: Grupo de Productos / Escala 7x24 Gestión desde Control Center | C22: Criterio 3 - Búsqueda y Selección de productos | D22: Asignar nombre al grupo de productos | E22: Una vez seleccionado al menos un producto se habilitará en la pantalla los siguientes botones: 3.9 Botón “Agregar”: Al dar clic a esta opción debe actualizar la pantalla con la información del criterio 4. | F22: Mostrar botón de agregar una vez se haya seleccionado un producto. | G22: Esta opción únicamente se habilita si el usuario ingresa un nombre de grupo válido y selecciona al menos un producto. | H22: Mostrar botón de agregar y al hacer clic mostrará el resumen del grupo de producto. | I22: Todos
A23: CP22 | B23: Grupo de Productos / Escala 7x24 Gestión desde Control Center | C23: Criterio 3 - Búsqueda y Selección de productos | D23: Asignar nombre al grupo de productos | E23: 3.10 Mensajería Error: En caso que un país no esté en la capacidad de responder la solicitud de productos se debe mostrar mensaje “La información de (país) no carga,Intente más tarde”, el canal debe mostrar en pantalla la información de los productos de los países que retornan la información por si el usuario requiere continuar con el proceso. | F23: Validación de mensajes de error de acuerdo al catálogo de errores | G23: - Mostrar error en caso no cargue la información de los productos a adicionar | H23: Validación de mensajes de error de acuerdo al catálogo de errores | I23: Todos
A24: CP23 | B24: Grupo de Productos / Escala 7x24 Gestión desde Control Center | C24: Criterio 5 - Resumen | D24: Selección de productos para crear el grupo de productos | E24: Resumen: El canal deberá mostrar: 4.1 Título del Header: Resumen. 4.2 Elemento regresar: Debe existir un botón o elemento que le permita al usuario regresar a la pantalla anterior en cualquier momento. 4.3 Nombre del Grupo: Se debe mostrar el nombre del grupo de producto ingresado en el criterio 2. | F24: En esta pantalla el canal debe guardar la información ingresada de la pantalla anterior y actualizará una nueva pantalla donde el usuario tendrá un resumen visual de cómo sería creado el grupo si no se realiza ninguna edición, esta pantalla permite “confirmar”, agregar más productos, guardar o eliminar si así lo requiere | H24: Mostrar el resumen del grupo producto de acuerdo a lo ingresado en el criterio 2 y 3 | I24: Todos
A25: CP24 | B25: Grupo de Productos / Escala 7x24 Gestión desde Control Center | C25: Criterio 5 - Resumen | D25: Selección de productos para crear el grupo de productos | E25: 4.4 Resumen: Deberá informar: Países: Banderas origen de los países de los productos que conforman el grupo de producto. Empresas: Número del total de empresas que conforman el grupo de productos. Productos: Número del total de productos seleccionados en el paso anterior. Tipo Productos: nombre del tipo de productos, ejemplo: Cuentas de ahorros / Cuenta Corriente. | F25: Este paso es la “confirmación”, el canal deberá mostrar un resumen general de las características principales de los productos seleccionados en el paso anterior | G25: - Mostrar campos en formato lectura | H25: Visualizar el detalle del grupo de producto, de acuerdo a la información ingresada en el criterio 2 y 3 | I25: Todos
A26: CP25 | B26: Grupo de Productos / Escala 7x24 Gestión desde Control Center | C26: Criterio 5 - Resumen | D26: Selección de productos para crear el grupo de productos | E26: 4.5 Productos Seleccionados: País: Se debe mostrar la bandera del país origen al que pertenece el producto seleccionado. Empresa: Se debe mostrar la empresa a la que pertenece el producto seleccionado. Nombre del producto: Se debe mostrar el nombre o alias del producto seleccionado Tipo de Producto: Se debe presentar la naturaleza del producto seleccionado. Número del Producto: Se debe presentar el número de producto seleccionado enmascarado. Eliminar: Al lado de cada registro debe estar un elemento que permita “eliminar” de manera individual si el usuario así lo requiere. Si el usuario da clic actualiza la pantalla y debe mostrar el mensaje ”producto desmarcado” con una opción de deshacer por si el usuario quiere revertir la acción. | F26: En la pantalla el canal mostrará la información de los productos seleccionados en el mismo orden del paso anterior agrupando la información por tipo de productos. | G26: - En este paso podrá eliminar los grupos de productos antes de proceder a la confirmación | H26: Visualizar el detalle del grupo de producto, de acuerdo a la información ingresada en el criterio 2 y 3 | I26: Todos
A27: CP26 | B27: Grupo de Productos / Escala 7x24 Gestión desde Control Center | C27: Criterio 5 - Resumen | D27: Selección de productos para crear el grupo de productos | E27: 4.6 Paginación: La paginación debe tener las siguientes características teniendo en cuenta que es una experiencia transversal en varias experiencias. La paginación se debe presentar en la parte superior del resultado, se presentará hasta 50 registros por página, de acuerdo la información obtenida del resultado de la consulta, para llegar a la parte inferior el usuario podrá usar el scroll y el teclado. | F27: Se debe presentar la paginación mostrando el número de páginas totales que arroja el resultado | H27: Mostrar paginación a partir de los 50 registros. | I27: Todos
A28: CP27 | B28: Grupo de Productos / Escala 7x24 Gestión desde Control Center | C28: Criterio 5 - Resumen | D28: Selección de productos para crear el grupo de productos | E28: 4.7 Elemento Back to top: El canal debe tener un elemento en pantalla que al dar clic lo debe llevar a la parte superior de la pantalla esto en caso que el cliente haga scroll para llegar a la parte inferior del resultado. | F28: Mostrar elemento de Back to top y al hacer clic permitir al usuario retornar a la parte superior de la pantalla | H28: Mostrar elemento de Back to top y al hacer clic permitir al usuario retornar a la parte superior de la pantalla | I28: Todos
A29: CP28 | B29: Grupo de Productos / Escala 7x24 Gestión desde Control Center | C29: Criterio 5 - Resumen | D29: Selección de productos para crear el grupo de productos | E29: 4.8 Editar grupo: Si el usuario requiere editar la selección de productos del grupo debe dar clic en regresar donde puede realizar esta novedad. | F29: Al dar clic en esta opción el canal debe llevar al usuario a la pantalla anterior con la preselección realizada. | H29: Mostrar selección de productos previamente realizada. | I29: Todos
A30: CP29 | B30: Grupo de Productos / Escala 7x24 Gestión desde Control Center | C30: Criterio 5 - Resumen | D30: Selección de productos para crear el grupo de productos | E30: 4.9 Botón “Crear grupo": Una vez el usuario de clic al botón se debe actualizar la pantalla y mostrar el resumen del grupo de productos. | F30: Visualizar botón de 'Crear Grupo' | H30: Acceso al botón 'Crear Grupo'. la gestión quedará pendiente de autorización | I30: Todos
A31: CP30 | B31: Grupo de Productos / Escala 7x24 Gestión desde Control Center | C31: Criterio 5 - Resumen | D31: Selección de productos para crear el grupo de productos | E31: 4.10 Mensajería: En caso que el usuario de clic a alguna parte del sidebar intentando ir a otro módulo se debe presentar mensaje “¿Quiere abandonar la asignación de grupo de producto? Si abandona debe empezar de cero con la asignación.” seguido de las opciones de volver/ Abandonar Este mensaje puede aparecer en cualquier paso desde la creación desde el criterio 2.3 hasta el este punto. | F31: Mostrar mensaje de error en caso el usuario BO quiera salirse de la gestión de grupo de producto. | H31: Validación de mensaje cuando el usuario haga clic en otra opción de CC | I31: Todos
A32: CP31 | B32: Grupo de Productos / Escala 7x24 Gestión desde Control Center | C32: Criterio 5 - Resumen | D32: Confirmación del grupo de producto | E32: Luego de confirmar la creación del grupo producto mostrará la pantalla de resultado indicando que la gestión se encuentra pendiente de autorización y mostrar el detalle del grupo producto | F32: Mostrar resumen del grupo producto | G32: - Mostrar campos en formato lectura | H32: - Gestión pendiente de autorización. | I32: Todos
A33: CP32 | B33: Grupo de Productos / Escala 7x24 Gestión desde Control Center | C33: Criterio 6 - Consulta grupos de productos | D33: Tener creado al menos un grupo de producto. | E33: Para ingresar a esta opción debe ingresar por Administración/Grupo de productos En esta pantalla el usuario tendrá la visual de todos los “grupos de productos” creados donde podrá aplicar filtros para encontrar un “grupo de productos” de manera sencilla, visualizar un mayor detalle de un grupo creado, editar o eliminar un grupo ya sea de manera individual o masiva, así: 6.1 Título: Grupos de productos Regresar: Debe existir un elemento que permita regresar a la pantalla anterior al darle clic. Descripción: Aquí puede crear, consultar y editar los grupos de productos. Para facilitar su gestión, puede usar el buscador o los filtros presentados. | F33: Se debe habilitar una opción que permita al usuario administrador visualizar, editar o eliminar los grupos de productos creados, teniendo en cuenta que el canal debe guiar al usuario. | G33: - En caso que el usuario elimine todos grupos de productos creados el canal debe guiar al usuario desde el criterio 2. y la opción de consultas no estará disponible. | H33: -Acceso a consultas de grupo de productos. | I33: Todos
A34: CP33 | B34: Grupo de Productos / Escala 7x24 Gestión desde Control Center | C34: Criterio 6 - Consulta grupos de productos | D34: Tener creado al menos un grupo de producto. | E34: 6.2 Resultado consulta: Los títulos de las las columnas del resultado de productos son: Nombre del grupo: Se debe mostrar el nombre con el que se creó grupo ejemplo: “Tesorería Honduras” en caso que el grupo de productos haya sido marcado como “destacado” una estrella debe aparecer al lado del nombre. los grupos marcados como “destacados” debe visualizarse en la parte superior del resultado, La marcación de un grupo cómo destacado podrá ser realizada al consultar un grupo puntual. País: El canal debe mostrar las banderas de los productos que se encuentran incluidos en el grupo. Empresas: Se deben visualizar el número del total de las empresas de los productos que se encuentran incluidos en el grupo de productos. Destacado: Debe existir un elemento que permita a los usuarios marcar o desmarcar un grupo como “destacado”, los grupos marcados como destacado serán mostrados en la tarde superior de resultado de las pantallas donde aplique la selección de grupos de productos. Accionables: permite al usuario seleccionar si requiere ver un mayor detalle o eliminar un grupo de productos creado previamente. Paginación: Teniendo en cuenta que la experiencia de paginación es transversal en caso que el resultado de la consulta tenga más de 50 registros debe incluir una paginación. | F34: Una vez el usuario esté en la opción de consultas visualizará en esta pantalla el resultado de las consultas de grupos de productos creados previamente | H34: Mostrar los registros de los grupos permisos que ha sido creados anteriormente | I34: Todos
A35: CP34 | B35: Grupo de Productos / Escala 7x24 Gestión desde Control Center | C35: Criterio 6 - Consulta grupos de productos | D35: Tener creado al menos un grupo de producto. | E35: 6.3 Búsqueda avanzada de productos: El canal debe permitir al usuario buscar productos por por las siguientes opciones: Elemento “Buscar": Al dar clic se debe habilitar una barra de búsqueda que permite al usuario ingresar el nombre del Grupo de producto, el canal debe actualizar los resultados de búsqueda teniendo en cuenta el texto ingresado, se debe habilitar un botón de “cancelar” en caso que el usuario quiera eliminar esta búsqueda. En caso que el usuario ingrese un texto que no encuentre coincidencia el canal debe mostrar “La búsqueda de (texto ingresado) no presenta resultados.” Elemento “Filtrar”: Debe contar con un elemento que permite buscar productos con filtros específicos, al dar clic sobre el texto se sobrepone en la pantalla la información detallando los filtros que se podrán aplicar para la búsqueda de productos así: Título: Filtrar Botón “x”: Regresa a la pantalla anterior. Texto: Aplique las opciones de filtrado que desea: | F35: Realizar consultas de grupo de productos por medio de filtros. | H35: Consultar grupos de productos por medio de filtros y opciones de búsqueda. | I35: Todos
A36: CP35 | B36: Grupo de Productos / Escala 7x24 Gestión desde Control Center | C36: Criterio 6 - Consulta grupos de productos | D36: Tener creado al menos un grupo de producto. | E36: 6.3.1 Países: permite seleccionar uno o todos los países, la opción que aquí se muestre dependerá de donde el grupo tenga presencia mostrando únicamente los países donde tiene productos. 6.3.2 Empresa: Permite seleccionar una o todas las empresas del grupo de acuerdo a la selección de empresas que conforman el grupo de productos. En la parte inferior deben estar las opciones: “Borrar” y “aplicar” Botón “Borrar": al dar clic debe eliminar los filtros de búsqueda ingresados por el usuario. Botón “Aplicar”: Al dar clic el canal actualiza la pantalla donde muestra los grupos de productos, mostrando como resultado únicamente los grupos que cumplan con los criterios buscados, en caso que el usuario requiera seleccionar o eliminar alguna selección la podrá aplicar la novedad de manera manual. En la parte superior del resultado se debe mostrar el nombre del filtro aplicado y una opción en el mismo texto que permita “eliminar” el filtro. Adicional se debe habilitar el elemento de “borrar filtros” al dar clic elimina todos los filtros aplicados. | F36: Mostrará los campos países y empresas con los cuales permitirá realizar búsqueda de grupos de productos. | G36: En caso que el usuario aplique filtros y no encuentra coincidencia debe mostrar “La búsqueda no presenta resultados” | H36: Mostrar resultado de búsqueda de acuerdo a los filtros utilizados. | I36: Todos
A37: CP36 | B37: Grupo de Productos / Escala 7x24 Gestión desde Control Center | C37: Criterio 6 - Consulta grupos de productos | D37: Tener creado al menos un grupo de producto. | E37: 6.5 Accionable / Detalle: El canal debe permitir al usuario acceder desde la pantalla de resultados a una nueva pantalla donde el usuario podrá visualizar el detalle completo de cómo está conformado un grupo de productos. | F37: Consultar detalle del grupo de producto | H37: Consultar detalle del grupo de producto | I37: Todos
A38: CP37 | B38: Grupo de Productos / Escala 7x24 Gestión desde Control Center | C38: Criterio 7 - Detalle del grupo | D38: Tener creado al menos un grupo de producto. | E38: 7.1 Título: Detalle del grupo de producto 7.2 Elemento regresar: Debe existir un botón o elemento que le permita al usuario regresar a la pantalla anterior en cualquier momento. 7.3 Nombre del Grupo: Se debe mostrar el nombre del grupo de producto ingresado en la creación. 7.4 Resumen: El canal deberá mostrar un resumen general de las características principales de los productos previamente seleccionados, el cuadro deberá informar: Países: Banderas origen de los países de los productos que conforman el grupo de producto. Empresas: Número del total de empresas que conforman el grupo de productos. Productos: Número del total de productos seleccionados en el paso anterior. Tipo Productos: nombre del tipo de productos, ejemplo: Cuentas de ahorros / Cuenta Corriente. | F38: Al ingresar al detalle se debe visualizar de manera detallada el resumen del grupo de producto. | H38: Visualizar el detalle del grupo producto | I38: Todos
A39: CP38 | B39: Grupo de Productos / Escala 7x24 Gestión desde Control Center | C39: Criterio 7 - Detalle del grupo | D39: Tener creado al menos un grupo de producto. | E39: 7.5 Productos Seleccionados: En la pantalla el canal mostrará la información de los productos seleccionados en el mismo orden del paso anterior agrupando la información por tipo de productos. País: Se debe mostrar la bandera del país origen al que pertenece el producto seleccionado. Empresa: Se debe mostrar la empresa a la que pertenece el producto seleccionado. Nombre del producto: Se debe mostrar el nombre o alias del producto seleccionado Tipo de Producto: Se debe presentar la naturaleza del producto seleccionado. Número del Producto: Se debe presentar el número de producto seleccionado enmascarado. | F39: Mostrar la información del grupo de producto | G39: Campos se visualizaran en formato lectura. | H39: Mostrar detalle del grupo de producto. | I39: Todos
A40: CP39 | B40: Grupo de Productos / Escala 7x24 Gestión desde Control Center | C40: Criterio 7 - Detalle del grupo | D40: Tener creado al menos un grupo de producto. | E40: 7.6 Paginación: La paginación se debe presentar en la parte superior del resultado, se presentará hasta 50 registros por página, de acuerdo la información obtenida del resultado de la consulta, para llegar a la parte inferior el usuario podrá usar el scroll y el teclado. | F40: En la pantalla se debe presentar la paginación mostrando el número de páginas totales que arroja el resultado | H40: Mostrar paginación de los resultados de los grupos de producto a partir de los 50 registros. | I40: Todos
A41: CP40 | B41: Grupo de Productos / Escala 7x24 Gestión desde Control Center | C41: Criterio 7 - Detalle del grupo | D41: Tener creado al menos un grupo de producto. | E41: 7.7 Elemento Back to top: El canal debe tener un elemento en pantalla que al dar clic lo debe llevar a la parte superior de la pantalla esto en caso que el cliente haga scroll para llegar a la parte de inferior del resultado. | F41: Mostrar botón de Back to top para que el usuario pueda dirigirse a la parte superior de la pantalla | H41: Redireccionar a la parte superior de la pantalla. | I41: Todos
A42: CP41 | B42: Grupo de Productos / Escala 7x24 Gestión desde Control Center | C42: Criterio 7 - Detalle del grupo | D42: Tener creado al menos un grupo de producto. | E42: 7.8 Icono “Destacado”: Se debe incluir un tooltip “Destacado”. Debe existir un elemento que permita a los usuarios marcar o desmarcar un grupo como “favorito”, los grupos marcados como favoritos serán mostrados en la parte superior del resultado de las pantallas donde aplique la selección de grupos de productos. | F42: Mostrar botón informativo que permita margar a un grupo de producto como favorito | H42: Marcación exitosa de un grupo de producto como favorito. | I42: Todos
A43: CP42 | B43: Grupo de Productos / Escala 7x24 Gestión desde Control Center | C43: Criterio 7 - Detalle del grupo | D43: Tener creado al menos un grupo de producto. | E43: 7.9 Icono “Descarga”: Se debe incluir un tooltip “Descargar reporte”. Debe existir un elemento que le permita al usuario realizar la descarga de todo el detalle de cómo está confirmado el Grupo de productos con toda la información de todas las páginas, el usuario al dar clic actualiza la pantalla y el canal muestra: Titulo: Descargar Reporte Descripción: Si la descarga no se da de inmediato le enviaremos el archivo al buzón. Texto: Elija el formato PDF (.pdf) Una vez el cliente seleccione un formato se habilita el botón de “Descargar”. Si el usuario requiere realizar una descarga masiva debe seleccionar primero los checkbox y cuando tenga seleccionado al menos un registro el canal habilita la opción de “descargar selección” | F43: Descargar el detalle de los grupos de productos en formato PDF | H43: Descargar el detalle de los grupos de producto y validar el detalle. | I43: Todos
A44: CP43 | B44: Grupo de Productos / Escala 7x24 Gestión desde Control Center | C44: Criterio 7 - Detalle del grupo | D44: Tener creado al menos un grupo de producto. | E44: Descarga en formato PDF, se deberá mostrar la siguiente información: Nombre del banco en la parte superior Fecha y hora de descarga: Se debe presentar la fecha y hora de la descarga del archivo dd/mm/aaaa hh/mm am-pm Título: Detalle Grupo regional Nombre del grupo regional: Se debe mostrar el nombre con el que fue creado. Países: Se debe mostrar las banderas del país de origen que conforman el grupo. Productos: Debe mostrar el número de productos que conforman el Grupo de productos Empresas: Debe mostrar la cantidad de empresas que tiene asociadas el Grupo de productos. Tipo de productos: debe mostrar la naturaleza por tipo de producto que lo conforma. Tabla de resultados: contenido de la consulta en la parte inferior de manera ordenada y clara con información de las columnas: País, Empresa (se debe mostrar el nombre completo), nombre del producto(se debe mostrar el nombre completo), tipo de producto, Número del producto (enmascarado). | F44: Al ingresar al detalle del archivo descargado debe permitir visualizar la información completa de los grupos de producto. | H44: Ingreso al archivo descargado y Validación del detalle con la información compelta del grupo de producto. | I44: Todos
A45: CP44 | B45: Grupo de Productos / Escala 7x24 Gestión desde Control Center | C45: Criterio 7 - Detalle del grupo | D45: Tener creado al menos un grupo de producto. | E45: Mensajería: - Si la descarga se realiza de manera satisfactoria actualiza la pantalla e informa en la parte superior “Descarga exitosa” - Si la generación del reporte no se puede realizar en línea por el tamaño se debe mostrar el siguiente modal: “El reporte se enviará al buzón de notificaciones del módulo regional.” - En caso que la descarga no se pueda generar por algún error se debe presentar mensaje: “Descarga fallida. Intente más tarde” | F45: Mostrar mensajes de acuerdo al resultado obtenido de la descarga de los grupos productos. | H45: Visualización de mensajes informativos de acuerdo al resultado de la búsqueda. | I45: Todos
A46: CP45 | B46: Grupo de Productos / Escala 7x24 Gestión desde Control Center | C46: Criterio 7 - Detalle del grupo | D46: Tener creado al menos un grupo de producto. | E46: 7.10 Icono “Editar”: Se debe incluir un tooltip “Editar”, al dar clic a este botón debe actualizar la pantalla y mostrar el nombre ingresado durante la creación, el nombre se debe mostrar de manera editable permitiendo cambiar o confirmar el nombre asignado, una vez el usuario de clic al botón “asignar” debe actualizar nuevamente la pantalla y continuar con el flujo desde el criterio 2.3 al criterio 5. pasando por la selección de productos, resumen y resultado, los productos que se muestran en la “selección” se deben mostrarse de manera preseleccionada teniendo en cuenta los que conforman el grupo. | F46: Permitir al usuario modificar un grupo de producto | H46: La gestión quedará con estado pendiente de autorización. | I46: Todos
A47: CP46 | B47: Grupo de Productos / Escala 7x24 Gestión desde Control Center | C47: Criterio 7 - Detalle del grupo | D47: Tener creado al menos un grupo de producto. | E47: 7.11 Icono “Eliminar”: Se debe incluir un tooltip “eliminar grupo” al dar clic se debe presentar la mensajería según aplique del criterio 9, teniendo en cuenta el flujo el usuario deberá confirmar la eliminación incluyendo la regla definida de retar al usuario ingresando la clave de confirmación, funcionalidad transversal de acuerdo a lo planteado en la: HU017_PER - Autorizaciones transversal | F47: Eliminar un grupo de producto previamente creado | H47: Eliminación exitosa de un grupo de producto. | I47: Todos
A48: CP47 | B48: Grupo de Productos / Escala 7x24 Gestión desde Control Center | C48: Criterio 8 - Edición grupos de productos | D48: Tener creado al menos un grupo de producto. | E48: Pantalla que debe mostrar la información pre diligenciada 8.1 Nombre de grupo: El canal debe actualizar la pantalla y mostrar el nombre ingresado durante la creación, el nombre se debe mostrar de manera editable permitiendo cambiar o confirmar el nombre asignado cómo en el criterio 2.3, una vez el usuario de clic al botón “asignar” debe actualizar nuevamente la pantalla y continuar con el flujo. | F48: Dentro de la opción de detalle del Grupo de producto creado previamente debe existir un elemento que permita al usuario realizar la edición del grupo de productos, al dar clic en esta opción se debe actualizar la pantalla y debe permitir visualizar y editar toda la información del grupo de producto. | H48: Editar el nombre del grupo producto. | I48: Todos
A49: CP48 | B49: Grupo de Productos / Escala 7x24 Gestión desde Control Center | C49: Criterio 8 - Edición grupos de productos | D49: Tener creado al menos un grupo de producto. | E49: 8.2 Productos seleccionados: En la pantalla el canal mostrará la información de los productos seleccionados en el mismo orden agrupando la información por tipo de productos, en esta pantalla al lado del producto seleccionado mostrará un icono que hará referencia a eliminar de manera individual el producto seleccionado, adicional deberá contar con una opción (checkbox) que muestra los productos seleccionados y permita al usuario adicionar o desmarcar de acuerdo a lo que requiere (criterio 3.8) | F49: Permitir al usuario agregar y quitar productos del grupo | H49: Eliminar y agregar productos correctamente. | I49: Todos
A50: CP49 | B50: Grupo de Productos / Escala 7x24 Gestión desde Control Center | C50: Criterio 8 - Edición grupos de productos | D50: Tener creado al menos un grupo de producto. | E50: 8.3 Resumen: Una vez seleccionados los nuevos productos el canal debe aplicar las reglas del criterio 4, donde tendrá la visual completa de cómo quedaría creado el nuevo grupo de productos. Mensajería: En la confirmación se debe presentar un modal que informe al usuario: “Una vez aprobada esta novedad, se actualizará los permisos a los usuarios y/o esquemas de firmas que tengas asignado este Grupo de Productos” | F50: Mostrar el resumen de la modificación del grupo de producto | G50: - El grupo de producto modificado tendrá validez una vez haya sido aprobado. | H50: Visualizar el resumen del grupo de producto modificado. | I50: Todos
A51: CP50 | B51: Grupo de Productos / Escala 7x24 Gestión desde Control Center | C51: Criterio 8 - Edición grupos de productos | D51: Tener creado al menos un grupo de producto. | E51: 8.4 Resultado: El canal debe aplicar las reglas del criterio 5 “resultado” teniendo en cuenta el tipo de administración que tenga el grupo regional y mostrar la información de acuerdo a las reglas ya definidas del criterio. | F51: Mostrar pantalla de resultados con la información del grupo a modificar. | G51: - Una vez se ejecute de autorización, el grupo de productos será actualizado de acuerdo a lo requerido por el usuario y la información debe actualizar en la opción de consultas. | H51: Gestión quedará pendiente de autorización. | I51: Todos
A52: CP51 | B52: Grupo de Productos / Escala 7x24 Gestión desde Control Center | C52: Criterio 9 - Eliminar grupos de productos | D52: Tener creado al menos un grupo de producto. | E52: Para la eliminación masiva debe permitir seleccionar varios registros, una vez marcados al menos un registro se habilita el botón “Eliminar seleccionados”. | F52: Mostrar un campo el cual permita seleccionar todos los grupos productos para poder eliminarlos | H52: Eliminación de todos los grupos productos. | I52: Todos
A53: CP52 | B53: Grupo de Productos / Escala 7x24 Gestión desde Control Center | C53: Criterio 9 - Eliminar grupos de productos | D53: Tener creado al menos un grupo de producto. | E53: Escenario Grupo a eliminar no está asignado a usuarios ni Esquemas de Firmas: En caso que el canal identifique que un grupo a eliminar no está asociado a un usuario ni a un esquema de firmas debe mostrar mensaje de confirmación previo a eliminación “ ¿Quiere eliminar el grupo de productos? seguido de las opciones “Volver/Eliminar” al dar clic en “eliminar | F53: Mostrar mensaje de confirmación previo a eliminación | H53: Visualización de mensaje informativo previo a la eliminación. | I53: Todos
A54: CP53 | B54: Grupo de Productos / Escala 7x24 Gestión desde Control Center | C54: Criterio 9 - Eliminar grupos de productos | D54: Tener creado al menos un grupo de producto. | E54: Modal de advertencia eliminación: En caso que el usuario intente eliminar un grupo de productos que se encuentre asociado a un usuario y/o a un esquema de firmas el canal deberá informar: - “¿Quiere eliminar el grupo de productos? Hay roles o esquemas que se asocian exclusivamente a este grupo. Si lo elimina, esos roles o esquemas no funcionarán dentro del módulo regional. Para que pueda usar el módulo, debe crearles un nuevo grupo de productos ” seguido de las opciones “Volver / Eliminar” Si el usuario da clic en “eliminar” el canal debe retar al usuario a ingresar el código de confirmación o clave según aplique y continuar con las aprobaciones de acuerdo al tipo de administración. | F54: Mostrar mensaje de confirmación previo a eliminación | H54: Visualización de mensaje informativo previo a la eliminación. | I54: Todos
A55: CP54 | B55: Grupo de Productos / Escala 7x24 Gestión desde Control Center | C55: Criterio 9 - Eliminar grupos de productos | D55: Tener creado al menos un grupo de producto. | E55: Escenario eliminación del único o todos los Grupo de Productos Una vez mostrado el mensaje “¿Quiere eliminar todos los grupos? Todos los roles y esquemas de firmas están asociados a estos grupos. Si los elimina, deberá crear nuevos grupos de productos para asignar a los roles y agregar las firmas.” posterior se muestran las opciones Volver/Eliminar. Una vez confirmado con las firmas requeridas, el canal deshabilita la opción de consultas de grupos de productos y debe mostrar el flujo para la creación del criterio 2. | F55: En caso que el usuario desee realizar la eliminación del único o de todos los grupos de productos, el canal debe permitir realizar la eliminación, siguiendo las reglas anteriores. | I55: Todos
A56: CP55 | B56: Grupo de Productos / Escala 7x24 Gestión desde Control Center | C56: Criterio 9 - Eliminar grupos de productos | D56: Tener creado al menos un grupo de producto. | E56: Teniendo en cuenta que el usuario puede tener habilitados usuarios dentro del módulo regional y/o esquemas de firmas las opciones del submódulo aparecerán disponibles pero con un elemento de “alerta”, una vez el usuario de clic tendrá la visual de consultas donde en la columna de estado visualizará “inconsistencia” al ingresar a cada opción tendrá mayor detalle que se encontrará en la H.U. de Administración de usuarios y Administración esquema de firma. | F56: Mostrar alerta de inconsistencia en grupo de productos con un ícono de señalización | H56: Visualizar el ícono de alerta en los grupos de productos. | I56: Todos
A57: CP56 | B57: Grupo de Productos / Escala 7x24 Gestión desde Control Center | C57: Criterio 9 - Eliminar grupos de productos | D57: Tener creado al menos un grupo de producto. | E57: En caso que se presente error en el momento de ejecutar la solicitud se debe presentar el mensaje “Eliminación fallida. Intente más tarde” | F57: Mostrar mensaje de error de acuerdo al catálogo de errores | H57: No ejecutará la eliminación. | I57: Todos
A58: CP57 | B58: Grupo de Productos / Escala 7x24 Gestión desde Control Center | C58: Criterio 9 - Eliminar grupos de productos | D58: Tener creado al menos un grupo de producto. | E58: Resultado: Mostrará mensaje indicando que la gestión de eliminación de grupo de producto se encuentra pendiente de autorización. | F58: Mostrar mensaje de resultado. | H58: Gestión pendiente de autorización | I58: Todos
A59: CP58 | B59: Grupo de Productos / Escala 7x24 Gestión desde Canal | C59: Criterio 1 Características Grupo de Productos | D59: Realizar la gestión con usuario con perfilamiento de operador | E59: Se debe habilitar una opción que permita a los usuarios con el perfilamiento de grupos de productos dentro del nuevo módulo regional crear, editar, consultar o eliminar grupo de productos que facilitarán la asignación de productos a los usuarios y a los esquemas de firmas definidos. | F59: Visualización a la funcionalidad de grupo de productos. | G59: - Crear grupo de producto con esquema administrativo simple. | H59: Acceso a la funcionalidad de grupo de productos desde el canal. | I59: Todos
A60: CP59 | B60: Grupo de Productos / Escala 7x24 Gestión desde Canal | C60: Criterio 1 Características Grupo de Productos | D60: Realizar la gestión con usuario con perfilamiento de operador | E60: Los productos a los que el usuario operador puede acceder para autogestionar las novedades de grupos de productos corresponde únicamente de productos asignados a la empresa desde el control center. | F60: Autogestionar grupo de productos | G60: - Cliente deberá tener productos activos | H60: Autogestionar grupo de productos | I60: Todos
A61: CP60 | B61: Grupo de Productos / Escala 7x24 Gestión desde Canal | C61: Criterio 1 Características Grupo de Productos | D61: Realizar la gestión con usuario con perfilamiento de operador | E61: Todos los textos cómo modales deben ser incluidos por una herramienta de gestión de contenidos o CMS paramétricos en caso que cuando tengamos los siguientes incrementales se puedan editar de manera sencilla. | F61: Poseer una herramienta de gestión de contenidos que permita hacer modificaciones a los grupos de productos cuando se les realicen cambios. | H61: Modificar los grupos de productos de forma exitosa | I61: Todos
A62: CP61 | B62: Grupo de Productos / Escala 7x24 Gestión desde Canal | C62: Criterio 1 Características Grupo de Productos | D62: Realizar la gestión con usuario con perfilamiento de operador | E62: Una vez el usuario acceda a esta funcionalidad mientras carga la información que se mostrará en pantalla, se debe mostrar el “Skeleton” de la funcionalidad. | F62: Visualizar la estructura de la funcionalidad con grupos de productos, roles y esquema de firmas | H62: Mostrar los campos que contiene la funcionalidad en formato lectura | I62: Todos
A63: CP62 | B63: Grupo de Productos / Escala 7x24 Gestión desde Canal | C63: Criterio 1 Características Grupo de Productos | D63: Realizar la gestión con usuario con perfilamiento de operador | E63: Si el usuario visualiza el contenido en inglés los textos del canal deben corresponder. | F63: Permitir al usuario gestionar grupo de productos en idioma inglés | G63: - Ejeuctar el flujo completo con esquema administrativo iSmple y Dual | H63: Mostrar traducidos los campos al inglés y oermitir ejecutar la gestión. | I63: Todos
A64: CP63 | B64: Grupo de Productos / Escala 7x24 Gestión desde Canal | C64: Criterio 2 - Creación Grupo de Productos | D64: Realizar la gestión con usuario con perfilamiento de operador | E64: Al ingresar a la funcionalidad de grupo de productos debe visualizar las opciones del módulo: Grupos de productos Descripción: Cree y administre los grupos de productos Roles Descripción: Asigne los roles según el acceso que le dará a cada usuario. Esquemas de firmas Descripción: Agregue las firmas de las personas que pueden dar autorizaciones. | F64: Mostrar información del detalle de las opciones del módulo | G64: - Crear grupo de producto con esquema administrativo simple. | H64: Visualización de la descripción de los campos en formato lectura | I64: Todos
A65: CP64 | B65: Grupo de Productos / Escala 7x24 Gestión desde Canal | C65: Criterio 2 - Creación Grupo de Productos | D65: Realizar la gestión con usuario con perfilamiento de operador | E65: El usuario operador podrá crear los grupos de productos que desee, una vez el usuario de clic a “Grupo de productos” el canal debe identificar si el usuario ya ha creado antes o es la primera vez teniendo en cuenta el flujo podrá ser: 2.1 Flujo Primera vez: Cuando sea la primera vez que el usuario administrador ingresa al módulo de administración el canal debe guiar al usuario a realizar una creación de “grupo de productos”, teniendo en cuenta lo anterior esta será la única opción habilitada al usuario, al dar clic debe actualizar la pantalla y mostrar el flujo del criterio 2.3. | F65: Mostrar al usuario una guía para crear por primera vez el grupo de productos | G65: - Crear grupo de producto con esquema administrativo simple. - El canal debe hacer la validación que es primera vez que el usuario ejecuta esta acción y no volver a mostrarlo una segunda vez. | H65: El usuario pueda visualizar la guia para la creación del grupo de producto por primera vez. | I65: Todos
A66: CP65 | B66: Grupo de Productos / Escala 7x24 Gestión desde Canal | C66: Criterio 2 - Creación Grupo de Productos | D66: Realizar la gestión con usuario con perfilamiento de operador | E66: 2.2 Flujo Creación Regular: Si existe un grupo creado previamente el usuario accede a la visual de Grupos creados y debe estar habilitado el botón para “Crear grupo” una vez de clic continua con el flujo del criterio 2.3. | F66: Mostrar boton de 'Crear grupo' | G66: - Crear grupo de producto con esquema administrativo simple. | H66: Habilitar el botón Crear grupo | I66: Todos
A67: CP66 | B67: Grupo de Productos / Escala 7x24 Gestión desde Canal | C67: Criterio 2 - Creación Grupo de Productos | D67: Realizar la gestión con usuario con perfilamiento de operador | E67: 2.3 Creación Grupo: Título: Nombre del grupo de productos Elemento para regresar | F67: Describir el nombre de la funcionalidad | G67: - Crear grupo de producto con esquema administrativo simple. - Mostrar campos en formato lectura | H67: Mostrar campos en formato lectura | I67: Todos
A68: CP67 | B68: Grupo de Productos / Escala 7x24 Gestión desde Canal | C68: Criterio 2 - Creación Grupo de Productos | D68: Realizar la gestión con usuario con perfilamiento de operador | E68: Descripción: Asigne un nombre al nuevo grupo de productos Espacio para el nombre: Se habilita la opción para que el usuario ingrese el nombre del grupo de productos que creará. Características del campo: - Alfanumérico. - Longitud máxima de 50 caracteres, debe habilitar un contador de caracteres que muestre al usuario la longitud máxima, los caracteres usados y los caracteres disponibles. - Longitud mínima de 5 caracteres, si no cumple con esta característica no permite continuar la creación, debe tener un elemento informe “ la longitud mínima es de 5 caracteres”. - Debe validar que el nombre ingresado sea único para el grupo regional, es decir no podrá tener el nombre repetido, en caso que intente crear un grupo con el mismo nombre el canal debe mostrar mensaje: “Este nombre ya se usó en otro grupo regional. Asigne uno nuevo” | F68: Permitir al usuario asignar un nombre personalizado al grupo de productos | G68: - Crear grupo de producto con esquema administrativo simple. | H68: Asignar nombre personalizado al grupo de producto | I68: Todos
A69: CP68 | B69: Grupo de Productos / Escala 7x24 Gestión desde Canal | C69: Criterio 2 - Creación Grupo de Productos | D69: Realizar la gestión con usuario con perfilamiento de operador | E69: Botón de “Asignar” permita continuar con el proceso de creación del Grupo de productos. | F69: Accesibilidad al botón de agregar | G69: - Mostrará botón de asignar cuando se haya colocado un nombre al grupo de producto - Crear grupo de producto con esquema administrativo simple. | H69: Visualización y acceso al botón de 'Asignar' | I69: Todos
A70: CP69 | B70: Grupo de Productos / Escala 7x24 Gestión desde Canal | C70: Criterio 3 - Búsqueda y Selección de productos | D70: Asignar nombre al grupo de productos | E70: Pantalla: 3.1 Título del Header: “Elección de productos” 3.2 Elemento regresar: Debe existir un botón o elemento que le permita al usuario regresar a la pantalla anterior en cualquier momen. | F70: El canal debe actualizar la pantalla para sugerir al usuario realizar la selección de los productos que conformarán el grupo de productos que está creando. | G70: - Se debe presentar todos los productos que tienen las empresas que conforman el grupo regional de acuerdo a lo parametrizado en el control center regional. - Crear grupo de producto con esquema administrativo simple. | H70: Visualizar título de la pantalla y botón de regresar | I70: Todos
A71: CP70 | B71: Grupo de Productos / Escala 7x24 Gestión desde Canal | C71: Criterio 3 - Búsqueda y Selección de productos | D71: Asignar nombre al grupo de productos | E71: 3.3 Títulos por columnas del resultado de productos: País: Debe mostrar bandera e iniciales del país al que pertenece el producto Empresa: Debe mostrar el nombre de la empresa a la que pertenece el producto. Nombre del Producto: se debe mostrar el nombre o el alias si está asignado de lo contrario mostrará el nombre de la empresa. Tipo de producto: Debe mostrar el tipo de la cuenta a la que pertenece el producto ( Cuenta ahorro, cuenta corriente, cuenta ahorro maestra) Número de producto: debe mostrar el número de la cuenta enmascarado. Checkbox: debe tener por cada fila de resultado este elemento que permite realizar selección de manera individual. | F71: - Permitir al usuario seleccionar el producto para la creación del grupo de productos. - Marcar y desmarcar productos de forma correcta | G71: - Visualizar las cuentas de las sociedades con las cuales se ingresó al módulo regional. - Crear grupo de producto con esquema administrativo simple. | H71: Selección de productos de forma exitosa. | I71: Todos
A72: CP71 | B72: Grupo de Productos / Escala 7x24 Gestión desde Canal | C72: Criterio 3 - Búsqueda y Selección de productos | D72: Asignar nombre al grupo de productos | E72: 3.4 Paginación: En la pantalla se debe presentar la paginación mostrando el número de páginas totales que arroja la consulta. - La paginación se debe presentar en la parte superior del resultado. - Se presentarán hasta 50 registros por página, de acuerdo a la información obtenida del resultado de la consulta, para llegar a la parte inferior el usuario podrá usar el scroll y el teclado. | F72: - La paginación se presentará de acuerdo al resultado de la búsqueda | G72: - Si no posee 50 registros no mostrará paginación. - Crear grupo de producto con esquema administrativo simple. | H72: Mostrará paginación a partir de los 50 registros | I72: Todos
A73: CP72 | B73: Grupo de Productos / Escala 7x24 Gestión desde Canal | C73: Criterio 3 - Búsqueda y Selección de productos | D73: Asignar nombre al grupo de productos | E73: 3.5 Opción para operar con todos los productos: El canal debe contar con una opción que permite al usuario seleccionar si desea “operar con todos los productos”. Una vez seleccionado se muestra la totalidad de los productos marcados de forma automática en el checkbox. | F73: Permitir seleccionar todos los registros con un solo clic en el botón de checkbox y al seleccionarlo se marquen automáticamente todos los productos del mismo tipo o de manera individual. | G73: - Crear grupo de producto con esquema administrativo simple. | H73: Marcación de todos los productos de forma exitosa. | I73: Todos
A74: CP73 | B74: Grupo de Productos / Escala 7x24 Gestión desde Canal | C74: Criterio 3 - Búsqueda y Selección de productos | D74: Asignar nombre al grupo de productos | E74: 3.6 Búsqueda avanzada de productos Buscar: Al dar clic se debe habilitar una barra de búsqueda que permite al usuario ingresar el nombre del producto, el canal debe actualizar los resultados de búsqueda teniendo en cuenta el texto ingresado, se debe habilitar un botón de “cancelar” en caso que el usuario quiera eliminar esta búsqueda. En caso que el usuario ingrese un texto que no encuentre coincidencia el canal debe mostrar “La búsqueda de (texto ingresado) no presenta resultados. Filtrar: Adicional debe contar con un elemento que permite buscar productos con filtros específicos, al dar clic sobre el texto se sobrepone en la pantalla la información detallando los filtros que se podrán aplicar para la búsqueda de productos así: Título: Filtrar Botón “x”: Regresa a la pantalla anterior. Texto: Aplique las opciones de filtrado que desea | F74: El canal debe permitir al usuario buscar productos por las funciones de Buscar y filtrar | G74: - Crear grupo de producto con esquema administrativo simple. | H74: Búsqueda y uso de filtros exitoso. | I74: Todos
... A102: CP101 | B102: Grupo de Productos / Escala 7x24 Gestión desde Canal | C102: Criterio 6 - Consulta grupos de productos | D102: Tener creado al menos un grupo de producto. | E102: 6.4 Descargar: Debe existir un elemento que le permita al usuario realizar la descarga de todos los grupos de productos creados y activos en el canal, el usuario al dar clic actualiza la pantalla y el canal muestra: Titulo: Descargar Reporte Descripción: Si la descarga no se da de inmediato le enviaremos el archivo al buzón. Texto: Elija el formato Excel (.xlsx) PDF (.pdf) Una vez el cliente seleccione un formato se habilita el botón de “Descargar”. En el formato en PDF en canal debe mostrar: Nombre del banco en la parte superior. Título: Grupo de productos Fecha y hora de descarga: Se debe mostrar la fecha y hora de descarga. Resultado: debe mostrar el contenido de la consulta en la parte inferior de manera ordenada y clara informando: El nombre del grupo de productos, país, cantidad de empresas asociadas y si el grupo fue marcado como destacado. Mensajería: - Si la descarga se realiza de manera satisfactoria actualiza la pantalla e informa en la parte superior “Descarga exitosa” - Si la generación del reporte no se puede realizar en línea por el tamaño se debe mostrar el siguiente modal: “El reporte se enviará al buzón de notificaciones del módulo regional.” - En caso que la descarga no se pueda generar por algún error se debe presentar mensaje: “Descarga fallida. Intente más tarde” | F102: Realizar descarga de búsqueda de acuerdo al tipo de formato seleccionado por el usuario | G102: - La información descargada debe coincidir si fue aplicado un filtro. El archivo descargado debe contener la información del total de resultados de todas las páginas que se muestran en el resultado. - Si el usuario requiere realizar una descarga masiva debe seleccionar primero los checkbox y cuando tenga seleccionado al menos un registro el canal habilita la opción de “descargar selección” | H102: Descargar reporte de consulta ejecutada de los grupos de productos en los formatos excel o PDF. | I102: Todos
A103: CP102 | B103: Grupo de Productos / Escala 7x24 Gestión desde Canal | C103: Criterio 6 - Consulta grupos de productos | D103: Tener creado al menos un grupo de producto. | E103: 6.5 Accionable / Detalle: El canal debe permitir al usuario acceder desde la pantalla de resultados a una nueva pantalla donde el usuario podrá visualizar el detalle completo de cómo está conformado un grupo de productos. | F103: Consultar detalle del grupo de producto | H103: Consultar detalle del grupo de producto | I103: Todos
A104: CP103 | B104: Grupo de Productos / Escala 7x24 Gestión desde Canal | C104: Criterio 7 - Detalle del grupo | D104: Tener creado al menos un grupo de producto. | E104: 7.1 Título: Detalle del grupo de producto 7.2 Elemento regresar: Debe existir un botón o elemento que le permita al usuario regresar a la pantalla anterior en cualquier momento. 7.3 Nombre del Grupo: Se debe mostrar el nombre del grupo de producto ingresado en la creación. 7.4 Resumen: El canal deberá mostrar un resumen general de las características principales de los productos previamente seleccionados, el cuadro deberá informar: Países: Banderas origen de los países de los productos que conforman el grupo de producto. Empresas: Número del total de empresas que conforman el grupo de productos. Productos: Número del total de productos seleccionados en el paso anterior. Tipo Productos: nombre del tipo de productos, ejemplo: Cuentas de ahorros / Cuenta Corriente. | F104: Al ingresar al detalle se debe visualizar de manera detallada el resumen del grupo de producto. | G104: - Acceso a detalle de grupo de productos a usuarios que posean el perfilamiento, operadores, maestros, autorizadores o usuarios con aprobación única. | H104: Visualizar el detalle del grupo producto | I104: Todos
A105: CP104 | B105: Grupo de Productos / Escala 7x24 Gestión desde Canal | C105: Criterio 7 - Detalle del grupo | D105: Tener creado al menos un grupo de producto. | E105: 7.5 Productos Seleccionados: En la pantalla el canal mostrará la información de los productos seleccionados en el mismo orden del paso anterior agrupando la información por tipo de productos. País: Se debe mostrar la bandera del país origen al que pertenece el producto seleccionado. Empresa: Se debe mostrar la empresa a la que pertenece el producto seleccionado. Nombre del producto: Se debe mostrar el nombre o alias del producto seleccionado Tipo de Producto: Se debe presentar la naturaleza del producto seleccionado. Número del Producto: Se debe presentar el número de producto seleccionado enmascarado. | F105: Mostrar la información del grupo de producto | G105: Campos se visualizaran en formato lectura. - Acceso a detalle de grupo de productos a usuarios que posean el perfilamiento, operadores, maestros, autorizadores o usuarios con aprobación única. | H105: Mostrar detalle del grupo de producto. | I105: Todos
A106: CP105 | B106: Grupo de Productos / Escala 7x24 Gestión desde Canal | C106: Criterio 7 - Detalle del grupo | D106: Tener creado al menos un grupo de producto. | E106: 7.6 Paginación: La paginación se debe presentar en la parte superior del resultado, se presentará hasta 50 registros por página, de acuerdo la información obtenida del resultado de la consulta, para llegar a la parte inferior el usuario podrá usar el scroll y el teclado. | F106: En la pantalla se debe presentar la paginación mostrando el número de páginas totales que arroja el resultado | G106: - Acceso a detalle de grupo de productos a usuarios que posean el perfilamiento, operadores, maestros, autorizadores o usuarios con aprobación única. | H106: Mostrar paginación de los resultados de los grupos de producto a partir de los 50 registros. | I106: Todos
A107: CP106 | B107: Grupo de Productos / Escala 7x24 Gestión desde Canal | C107: Criterio 7 - Detalle del grupo | D107: Tener creado al menos un grupo de producto. | E107: 7.7 Elemento Back to top: El canal debe tener un elemento en pantalla que al dar clic lo debe llevar a la parte superior de la pantalla esto en caso que el cliente haga scroll para llegar a la parte de inferior del resultado. | F107: Mostrar botón de Back to top para que el usuario pueda dirigirse a la parte superior de la pantalla | G107: - Acceso a detalle de grupo de productos a usuarios que posean el perfilamiento, operadores, maestros, autorizadores o usuarios con aprobación única. | H107: Redireccionar a la parte superior de la pantalla. | I107: Todos
